[{"spawnID":"1","spawnType":"Obstacle","eventType":"Dodge","eventCat":"Neutral","x":"-6.37321758","timeToReact":"99","screenV":"99","time":"8.630564"},{"spawnID":"5","spawnType":"Bonus","eventType":"Catch","eventCat":"Positive","x":"3.83169484","timeToReact":"4.33924744","screenV":"6.72415","time":"8.963505"},{"spawnID":"6","spawnType":"Obstacle","eventType":"Collision","eventCat":"Negative","x":"0.42115593","timeToReact":"4.421486","screenV":"5.94028","time":"9.293695"},{"spawnID":"7","spawnType":"Enemy","eventType":"Collision","eventCat":"Negative","x":"-1.28298","y":"-5.7381587","timeToReact":"4.439928","screenV":"5.93119","time":"9.830074"},{"spawnID":"2","spawnType":"Bonus","eventType":"Miss","eventCat":"Neutral","x":"-8.368568","timeToReact":"99","screenV":"99","time":"9.894495"},{"spawnID":"7","spawnType":"Enemy","eventType":"Hurt","eventCat":"Negative","x":"0","timeToReact":"5.1843074","screenV":"5.50071","time":"10.5744534"},{"spawnID":"7","spawnType":"Enemy","eventType":"Hurt","eventCat":"Negative","x":"0","timeToReact":"5.2511161","screenV":"5.43073","time":"10.6412621"},{"spawnID":"7","spawnType":"Enemy","eventType":"Hurt","eventCat":"Negative","x":"0.00186827069","timeToReact":"5.3149398","screenV":"5.36551","time":"10.7050858"},{"spawnID":"3","spawnType":"Enemy","eventType":"Miss","eventCat":"Neutral","x":"-0.143316269","y":"-25.3370781","timeToReact":"99","screenV":"99","time":"10.9681816"},{"spawnID":"4","spawnType":"Bonus","eventType":"Miss","eventCat":"Neutral","x":"-12.1100836","timeToReact":"99","screenV":"99","time":"11.0399246"},{"spawnID":"6","spawnType":"Obstacle","eventType":"Dodge","eventCat":"Neutral","x":"0.42115593","timeToReact":"99","screenV":"99","time":"11.7690277"},{"spawnID":"14","spawnType":"Enemy","eventType":"Kill","eventCat":"Positive","x":"4.373083","timeToReact":"2.6717739","screenV":"7.09663","time":"12.2467594"},{"spawnID":"14","spawnType":"Enemy","eventType":"Hit","eventCat":"Positive","x":"4.373083","timeToReact":"2.6720600","screenV":"7.09587","time":"12.2470455"},{"spawnID":"11","spawnType":"Bonus","eventType":"Catch","eventCat":"Positive","x":"4.43994856","timeToReact":"4.5211559","screenV":"6.52464","time":"12.5899639"},{"spawnID":"8","spawnType":"Bonus","eventType":"Miss","eventCat":"Neutral","x":"-8.237754","timeToReact":"99","screenV":"99","time":"13.3449326"},{"spawnID":"15","spawnType":"Bonus","eventType":"Catch","eventCat":"Positive","x":"4.05292034","timeToReact":"3.8590507","screenV":"6.73963","time":"14.2459087"},{"spawnID":"9","spawnType":"Bonus","eventType":"Miss","eventCat":"Neutral","x":"-5.44241142","timeToReact":"99","screenV":"99","time":"14.3181114"},{"spawnID":"12","spawnType":"Obstacle","eventType":"Dodge","eventCat":"Neutral","x":"-8.873626","timeToReact":"99","screenV":"99","time":"15.6298389"},{"spawnID":"17","spawnType":"Bonus","eventType":"Catch","eventCat":"Positive","x":"2.29611826","timeToReact":"4.6746234","screenV":"6.28540","time":"16.1999454"},{"spawnID":"13","spawnType":"Bonus","eventType":"Miss","eventCat":"Neutral","x":"10.9297915","timeToReact":"99","screenV":"99","time":"16.74698"},{"spawnID":"10","spawnType":"Enemy","eventType":"Miss","eventCat":"Neutral","x":"-15.3988829","y":"-24.840971","timeToReact":"99","screenV":"99","time":"17.081171"},{"spawnID":"20","spawnType":"Enemy","eventType":"Kill","eventCat":"Positive","x":"3.3401134","timeToReact":"3.8322182","screenV":"4.74557","time":"17.6122341"},{"spawnID":"20","spawnType":"Enemy","eventType":"Hit","eventCat":"Positive","x":"3.3401134","timeToReact":"3.8325341","screenV":"4.74518","time":"17.61255"},{"spawnID":"16","spawnType":"Obstacle","eventType":"Dodge","eventCat":"Neutral","x":"-4.19541073","timeToReact":"99","screenV":"99","time":"17.7373333"},{"spawnID":"23","spawnType":"Bonus","eventType":"Catch","eventCat":"Positive","x":"3.77254319","timeToReact":"4.2081776","screenV":"6.75658","time":"19.1722546"},{"spawnID":"18","spawnType":"Enemy","eventType":"Miss","eventCat":"Neutral","x":"-2.67239571","y":"-25.11073","timeToReact":"99","screenV":"99","time":"19.239748"},{"spawnID":"19","spawnType":"Bonus","eventType":"Miss","eventCat":"Neutral","x":"-7.93985653","timeToReact":"99","screenV":"99","time":"20.2119274"},{"spawnID":"25","spawnType":"Bonus","eventType":"Catch","eventCat":"Positive","x":"5.521342","timeToReact":"4.1965409","screenV":"6.73883","time":"20.2778645"},{"spawnID":"22","spawnType":"Obstacle","eventType":"Dodge","eventCat":"Neutral","x":"-6.114707","timeToReact":"99","screenV":"99","time":"20.72798"},{"spawnID":"21","spawnType":"Bonus","eventType":"Miss","eventCat":"Neutral","x":"-9.257815","timeToReact":"99","screenV":"99","time":"21.1339741"},{"spawnID":"24","spawnType":"Enemy","eventType":"Miss","eventCat":"Neutral","x":"9.787311","y":"-25.072979","timeToReact":"99","screenV":"99","time":"22.0328655"},{"spawnID":"28","spawnType":"Bonus","eventType":"Catch","eventCat":"Positive","x":"0.6109271","timeToReact":"4.7696457","screenV":"6.11682","time":"23.109148"},{"spawnID":"27","spawnType":"Enemy","eventType":"Hurt","eventCat":"Negative","x":"0.7208941","timeToReact":"5.5944023","screenV":"5.09748","time":"23.5433788"},{"spawnID":"29","spawnType":"Bonus","eventType":"Catch","eventCat":"Positive","x":"0.569935739","timeToReact":"4.2337990","screenV":"6.77940","time":"23.6914616"},{"spawnID":"26","spawnType":"Bonus","eventType":"Miss","eventCat":"Neutral","x":"7.14338541","timeToReact":"99","screenV":"99","time":"24.5545521"},{"spawnID":"27","spawnType":"Enemy","eventType":"Hurt","eventCat":"Negative","x":"1.35874093","timeToReact":"7.6434593","screenV":"3.73095","time":"25.5924358"},{"spawnID":"35","spawnType":"Bonus","eventType":"Catch","eventCat":"Positive","x":"0.145295575","timeToReact":"4.2603455","screenV":"6.37885","time":"25.8934155"},{"spawnID":"30","spawnType":"Obstacle","eventType":"Dodge","eventCat":"Neutral","x":"15.4145355","timeToReact":"99","screenV":"99","time":"26.3311062"},{"spawnID":"31","spawnType":"Obstacle","eventType":"Dodge","eventCat":"Neutral","x":"-14.9260521","timeToReact":"99","screenV":"99","time":"26.5435047"},{"spawnID":"33","spawnType":"Obstacle","eventType":"Dodge","eventCat":"Neutral","x":"6.263792","timeToReact":"99","screenV":"99","time":"27.2432461"},{"spawnID":"27","spawnType":"Enemy","eventType":"Miss","eventCat":"Neutral","x":"-6.50724554","y":"-24.9837322","timeToReact":"99","screenV":"99","time":"27.3819942"},{"spawnID":"38","spawnType":"Obstacle","eventType":"Collision","eventCat":"Negative","x":"0.2178173","timeToReact":"4.25160","screenV":"5.93987","time":"27.45209"},{"spawnID":"34","spawnType":"Bonus","eventType":"Miss","eventCat":"Neutral","x":"8.663042","timeToReact":"99","screenV":"99","time":"28.2412548"},{"spawnID":"44","spawnType":"Enemy","eventType":"Hurt","eventCat":"Negative","x":"-0.311265469","timeToReact":"2.9588547","screenV":"9.63798","time":"29.2375927"},{"spawnID":"44","spawnType":"Enemy","eventType":"Hurt","eventCat":"Negative","x":"-0.400343716","timeToReact":"3.0292587","screenV":"9.41398","time":"29.3079967"},{"spawnID":"44","spawnType":"Enemy","eventType":"Hurt","eventCat":"Negative","x":"-0.5712942","timeToReact":"3.1685333","screenV":"9.00018","time":"29.4472713"},{"spawnID":"44","spawnType":"Enemy","eventType":"Hurt","eventCat":"Negative","x":"-0.6555584","timeToReact":"3.237072","screenV":"8.80962","time":"29.51581"},{"spawnID":"44","spawnType":"Enemy","eventType":"Hurt","eventCat":"Negative","x":"-0.794571757","timeToReact":"3.3720589","screenV":"8.45696","time":"29.6507969"},{"spawnID":"44","spawnType":"Enemy","eventType":"Hurt","eventCat":"Negative","x":"-0.857933044","timeToReact":"3.4392395","screenV":"8.29177","time":"29.7179775"},{"spawnID":"38","spawnType":"Obstacle","eventType":"Dodge","eventCat":"Neutral","x":"0.2178173","timeToReact":"99","screenV":"99","time":"29.84978"},{"spawnID":"44","spawnType":"Enemy","eventType":"Hurt","eventCat":"Negative","x":"-0.9646301","timeToReact":"3.5721588","screenV":"7.98323","time":"29.8508968"},{"spawnID":"37","spawnType":"Bonus","eventType":"Miss","eventCat":"Neutral","x":"-11.034708","timeToReact":"99","screenV":"99","time":"30.1113529"},{"spawnID":"43","spawnType":"Bonus","eventType":"Catch","eventCat":"Positive","x":"-1.300985","timeToReact":"4.1033516","screenV":"7.05844","time":"30.3094044"},{"spawnID":"39","spawnType":"Obstacle","eventType":"Dodge","eventCat":"Neutral","x":"-8.029113","timeToReact":"99","screenV":"99","time":"30.37076"},{"spawnID":"36","spawnType":"Enemy","eventType":"Miss","eventCat":"Neutral","x":"3.9178412","y":"-25.1164379","timeToReact":"99","screenV":"99","time":"30.8891544"},{"spawnID":"40","spawnType":"Bonus","eventType":"Miss","eventCat":"Neutral","x":"-11.9953318","timeToReact":"99","screenV":"99","time":"30.8897877"},{"spawnID":"42","spawnType":"Bonus","eventType":"Miss","eventCat":"Neutral","x":"-8.999253","timeToReact":"99","screenV":"99","time":"31.6749744"},{"spawnID":"44","spawnType":"Enemy","eventType":"Miss","eventCat":"Neutral","x":"3.539054","y":"-25.2055683","timeToReact":"99","screenV":"99","time":"31.8043"},{"spawnID":"41","spawnType":"Enemy","eventType":"Miss","eventCat":"Neutral","x":"4.7417264","y":"-25.0068188","timeToReact":"99","screenV":"99","time":"32.3314171"},{"spawnID":"46","spawnType":"Obstacle","eventType":"Dodge","eventCat":"Neutral","x":"14.7113876","timeToReact":"99","screenV":"99","time":"33.5787964"},{"spawnID":"45","spawnType":"Bonus","eventType":"Miss","eventCat":"Neutral","x":"-11.6891861","timeToReact":"99","screenV":"99","time":"33.5804825"},{"spawnID":"48","spawnType":"Bonus","eventType":"Miss","eventCat":"Neutral","x":"4.44590664","timeToReact":"99","screenV":"99","time":"34.36041"},{"spawnID":"47","spawnType":"Enemy","eventType":"Miss","eventCat":"Neutral","x":"-7.47269726","y":"-25.1900463","timeToReact":"99","screenV":"99","time":"34.4239349"},{"spawnID":"49","spawnType":"Bonus","eventType":"Miss","eventCat":"Neutral","x":"11.4539509","timeToReact":"99","screenV":"99","time":"35.61172"},{"spawnID":"50","spawnType":"Bonus","eventType":"Catch","eventCat":"Positive","x":"10.02453","timeToReact":"4.058104","screenV":"6.68443","time":"45.19245"},{"spawnID":"52","spawnType":"Bonus","eventType":"Catch","eventCat":"Positive","x":"6.430592","timeToReact":"4.0123133","screenV":"6.52105","time":"46.28659"},{"spawnID":"55","spawnType":"Enemy","eventType":"Hit","eventCat":"Positive","x":"9.814541","timeToReact":"2.6187075","screenV":"6.26204","time":"46.7934875"},{"spawnID":"55","spawnType":"Enemy","eventType":"Kill","eventCat":"Positive","x":"9.814541","timeToReact":"2.9228572","screenV":"6.25043","time":"47.0976372"},{"spawnID":"55","spawnType":"Enemy","eventType":"Hit","eventCat":"Positive","x":"9.814541","timeToReact":"2.92296","screenV":"6.25021","time":"47.09774"},{"spawnID":"56","spawnType":"Bonus","eventType":"Catch","eventCat":"Positive","x":"1.32830429","timeToReact":"4.6163788","screenV":"6.38801","time":"49.1491966"},{"spawnID":"51","spawnType":"Enemy","eventType":"Miss","eventCat":"Neutral","x":"-14.218708","y":"-25.186142","timeToReact":"99","screenV":"99","time":"49.559063"},{"spawnID":"53","spawnType":"Bonus","eventType":"Miss","eventCat":"Neutral","x":"7.320322","timeToReact":"99","screenV":"99","time":"50.713726"},{"spawnID":"54","spawnType":"Obstacle","eventType":"Dodge","eventCat":"Neutral","x":"-11.6428528","timeToReact":"99","screenV":"99","time":"50.799366"},{"spawnID":"57","spawnType":"Obstacle","eventType":"Dodge","eventCat":"Neutral","x":"6.486391","timeToReact":"99","screenV":"99","time":"52.0179939"},{"spawnID":"59","spawnType":"Obstacle","eventType":"Dodge","eventCat":"Neutral","x":"-0.370542526","timeToReact":"99","screenV":"99","time":"52.4350624"},{"spawnID":"60","spawnType":"Obstacle","eventType":"Dodge","eventCat":"Neutral","x":"-11.4041672","timeToReact":"99","screenV":"99","time":"52.504406"},{"spawnID":"68","spawnType":"Enemy","eventType":"Hit","eventCat":"Positive","x":"-0.2748394","timeToReact":"2.5210113","screenV":"5.92977","time":"52.8395271"},{"spawnID":"61","spawnType":"Obstacle","eventType":"Dodge","eventCat":"Neutral","x":"10.6566839","timeToReact":"99","screenV":"99","time":"53.0377159"},{"spawnID":"68","spawnType":"Enemy","eventType":"Kill","eventCat":"Positive","x":"-0.2748394","timeToReact":"2.7205642","screenV":"5.93142","time":"53.03908"},{"spawnID":"68","spawnType":"Enemy","eventType":"Hit","eventCat":"Positive","x":"-0.2748394","timeToReact":"2.7206573","screenV":"5.93122","time":"53.0391731"},{"spawnID":"58","spawnType":"Bonus","eventType":"Miss","eventCat":"Neutral","x":"9.528231","timeToReact":"99","screenV":"99","time":"53.1686974"},{"spawnID":"66","spawnType":"Bonus","eventType":"Catch","eventCat":"Positive","x":"0","timeToReact":"4.4419632","screenV":"6.47358","time":"53.3665962"},{"spawnID":"68","spawnType":"Enemy","eventType":"Hurt","eventCat":"Negative","x":"0","timeToReact":"3.3883590","screenV":"8.41628","time":"53.7068748"},{"spawnID":"68","spawnType":"Enemy","eventType":"Hurt","eventCat":"Negative","x":"0","timeToReact":"3.5213165","screenV":"8.09850","time":"53.8398323"},{"spawnID":"63","spawnType":"Bonus","eventType":"Miss","eventCat":"Neutral","x":"-3.919085","timeToReact":"99","screenV":"99","time":"54.18247"},{"spawnID":"67","spawnType":"Bonus","eventType":"Catch","eventCat":"Positive","x":"-0.270143032","timeToReact":"4.6077194","screenV":"6.25484","time":"54.6771049"},{"spawnID":"64","spawnType":"Bonus","eventType":"Miss","eventCat":"Neutral","x":"-10.6969051","timeToReact":"99","screenV":"99","time":"55.4002647"},{"spawnID":"69","spawnType":"Obstacle","eventType":"Dodge","eventCat":"Neutral","x":"-9.306979","timeToReact":"99","screenV":"99","time":"57.19309"},{"spawnID":"70","spawnType":"Obstacle","eventType":"Dodge","eventCat":"Neutral","x":"-2.14460945","timeToReact":"99","screenV":"99","time":"57.8720131"},{"spawnID":"75","spawnType":"Obstacle","eventType":"Collision","eventCat":"Negative","x":"5.884306","timeToReact":"4.2961425","screenV":"6.04281","time":"58.1536369"},{"spawnID":"71","spawnType":"Bonus","eventType":"Miss","eventCat":"Neutral","x":"7.55360746","timeToReact":"99","screenV":"99","time":"58.55962"},{"spawnID":"77","spawnType":"Bonus","eventType":"Catch","eventCat":"Positive","x":"4.76551962","timeToReact":"4.14344","screenV":"6.81810","time":"58.76376"},{"spawnID":"72","spawnType":"Bonus","eventType":"Miss","eventCat":"Neutral","x":"-11.7682753","timeToReact":"99","screenV":"99","time":"59.7335625"},{"spawnID":"75","spawnType":"Obstacle","eventType":"Dodge","eventCat":"Neutral","x":"5.884306","timeToReact":"99","screenV":"99","time":"60.4766655"},{"spawnID":"74","spawnType":"Bonus","eventType":"Miss","eventCat":"Neutral","x":"-3.91791987","timeToReact":"99","screenV":"99","time":"60.678112"},{"spawnID":"81","spawnType":"Bonus","eventType":"Catch","eventCat":"Positive","x":"6.12744141","timeToReact":"4.0687564","screenV":"6.89460","time":"60.8727"},{"spawnID":"73","spawnType":"Enemy","eventType":"Miss","eventCat":"Neutral","x":"11.993145","y":"-25.03104","timeToReact":"99","screenV":"99","time":"61.74632"},{"spawnID":"82","spawnType":"Bonus","eventType":"Catch","eventCat":"Positive","x":"5.453847","timeToReact":"4.3176949","screenV":"6.55436","time":"62.27753"},{"spawnID":"78","spawnType":"Bonus","eventType":"Miss","eventCat":"Neutral","x":"-11.1915064","timeToReact":"99","screenV":"99","time":"63.0089226"},{"spawnID":"80","spawnType":"Obstacle","eventType":"Dodge","eventCat":"Neutral","x":"-8.374221","timeToReact":"99","screenV":"99","time":"63.20673"},{"spawnID":"84","spawnType":"Bonus","eventType":"Catch","eventCat":"Positive","x":"3.071466","timeToReact":"4.1424789","screenV":"6.92042","time":"63.2076225"},{"spawnID":"83","spawnType":"Enemy","eventType":"Miss","eventCat":"Neutral","x":"11.7156134","y":"-25.0131645","timeToReact":"99","screenV":"99","time":"64.676"},{"spawnID":"85","spawnType":"Bonus","eventType":"Catch","eventCat":"Positive","x":"3.09974742","timeToReact":"4.9187443","screenV":"6.45614","time":"65.0797043"},{"spawnID":"79","spawnType":"Enemy","eventType":"Miss","eventCat":"Neutral","x":"-12.3567247","y":"-25.0878048","timeToReact":"99","screenV":"99","time":"65.77602"},{"spawnID":"87","spawnType":"Bonus","eventType":"Catch","eventCat":"Positive","x":"5.681271","timeToReact":"4.9707427","screenV":"6.02157","time":"66.19943"},{"spawnID":"86","spawnType":"Enemy","eventType":"Miss","eventCat":"Neutral","x":"-1.48830211","y":"-25.1803837","timeToReact":"99","screenV":"99","time":"66.79217"},{"spawnID":"92","spawnType":"Bonus","eventType":"Catch","eventCat":"Positive","x":"1.52291846","timeToReact":"4.25281","screenV":"6.38085","time":"67.74324"},{"spawnID":"88","spawnType":"Obstacle","eventType":"Dodge","eventCat":"Neutral","x":"0.817651749","timeToReact":"99","screenV":"99","time":"68.55782"},{"spawnID":"89","spawnType":"Obstacle","eventType":"Dodge","eventCat":"Neutral","x":"-5.15975475","timeToReact":"99","screenV":"99","time":"68.62221"},{"spawnID":"93","spawnType":"Bonus","eventType":"Catch","eventCat":"Positive","x":"0.150602534","timeToReact":"4.19476","screenV":"6.76230","time":"68.75306"},{"spawnID":"98","spawnType":"Enemy","eventType":"Hit","eventCat":"Positive","x":"0.193307877","timeToReact":"2.47718","screenV":"5.98183","time":"69.29218"},{"spawnID":"98","spawnType":"Enemy","eventType":"Kill","eventCat":"Positive","x":"0.193307877","timeToReact":"2.73609","screenV":"5.99127","time":"69.55109"},{"spawnID":"98","spawnType":"Enemy","eventType":"Hit","eventCat":"Positive","x":"0.193307877","timeToReact":"2.73647","screenV":"5.99044","time":"69.55147"},{"spawnID":"90","spawnType":"Bonus","eventType":"Miss","eventCat":"Neutral","x":"-0.9696553","timeToReact":"99","screenV":"99","time":"69.74756"},{"spawnID":"95","spawnType":"Obstacle","eventType":"Dodge","eventCat":"Neutral","x":"-4.99397945","timeToReact":"99","screenV":"99","time":"72.00182"},{"spawnID":"91","spawnType":"Enemy","eventType":"Miss","eventCat":"Neutral","x":"-10.25387","y":"-24.9794025","timeToReact":"99","screenV":"99","time":"72.06774"},{"spawnID":"94","spawnType":"Enemy","eventType":"Miss","eventCat":"Neutral","x":"-9.299597","y":"-27.2670975","timeToReact":"99","screenV":"99","time":"72.7693558"},{"spawnID":"96","spawnType":"Bonus","eventType":"Miss","eventCat":"Neutral","x":"-7.665843","timeToReact":"99","screenV":"99","time":"72.95763"},{"spawnID":"101","spawnType":"Bonus","eventType":"Catch","eventCat":"Positive","x":"1.03564966","timeToReact":"4.1833153","screenV":"6.63006","time":"73.1580353"},{"spawnID":"97","spawnType":"Bonus","eventType":"Miss","eventCat":"Neutral","x":"12.3724165","timeToReact":"99","screenV":"99","time":"74.19081"},{"spawnID":"100","spawnType":"Enemy","eventType":"Miss","eventCat":"Neutral","x":"-8.866289","y":"-25.04665","timeToReact":"99","screenV":"99","time":"75.16557"},{"spawnID":"99","spawnType":"Bonus","eventType":"Miss","eventCat":"Neutral","x":"-6.13532448","timeToReact":"99","screenV":"99","time":"75.35663"},{"spawnID":"102","spawnType":"Obstacle","eventType":"Dodge","eventCat":"Neutral","x":"-4.74906445","timeToReact":"99","screenV":"99","time":"76.26398"},{"spawnID":"103","spawnType":"Bonus","eventType":"Catch","eventCat":"Positive","x":"5.73551035","timeToReact":"4.2660039","screenV":"6.53743","time":"85.41303"},{"spawnID":"108","spawnType":"Bonus","eventType":"Catch","eventCat":"Positive","x":"-0.2509779","timeToReact":"4.1008652","screenV":"6.79751","time":"88.6344452"},{"spawnID":"104","spawnType":"Enemy","eventType":"Miss","eventCat":"Neutral","x":"-1.79328728","y":"-25.0225372","timeToReact":"99","screenV":"99","time":"89.62728"},{"spawnID":"105","spawnType":"Bonus","eventType":"Miss","eventCat":"Neutral","x":"-7.14577246","timeToReact":"99","screenV":"99","time":"89.70408"},{"spawnID":"106","spawnType":"Bonus","eventType":"Miss","eventCat":"Neutral","x":"12.4401","timeToReact":"99","screenV":"99","time":"91.0009155"},{"spawnID":"116","spawnType":"Enemy","eventType":"Hit","eventCat":"Positive","x":"3.45964622","timeToReact":"2.62461","screenV":"5.87988","time":"91.00161"},{"spawnID":"113","spawnType":"Bonus","eventType":"Catch","eventCat":"Positive","x":"-0.173020437","timeToReact":"4.3917748","screenV":"6.41704","time":"91.07855"},{"spawnID":"109","spawnType":"Obstacle","eventType":"Dodge","eventCat":"Neutral","x":"5.191927","timeToReact":"99","screenV":"99","time":"92.2704"},{"spawnID":"111","spawnType":"Obstacle","eventType":"Dodge","eventCat":"Neutral","x":"15.2979393","timeToReact":"99","screenV":"99","time":"92.68659"},{"spawnID":"110","spawnType":"Bonus","eventType":"Miss","eventCat":"Neutral","x":"-5.318814","timeToReact":"99","screenV":"99","time":"93.08512"},{"spawnID":"107","spawnType":"Enemy","eventType":"Miss","eventCat":"Neutral","x":"7.38961458","y":"-25.0036545","timeToReact":"99","screenV":"99","time":"93.74309"},{"spawnID":"114","spawnType":"Obstacle","eventType":"Dodge","eventCat":"Neutral","x":"14.12608","timeToReact":"99","screenV":"99","time":"93.80273"},{"spawnID":"118","spawnType":"Obstacle","eventType":"Collision","eventCat":"Negative","x":"2.28302574","timeToReact":"4.2224348","screenV":"5.95118","time":"93.86882"},{"spawnID":"112","spawnType":"Enemy","eventType":"Hurt","eventCat":"Negative","x":"0.321479261","timeToReact":"7.5790846","screenV":"3.76264","time":"93.8717346"},{"spawnID":"115","spawnType":"Bonus","eventType":"Miss","eventCat":"Neutral","x":"-6.0425086","timeToReact":"99","screenV":"99","time":"95.45769"},{"spawnID":"112","spawnType":"Enemy","eventType":"Miss","eventCat":"Neutral","x":"-7.34303141","y":"-25.005434","timeToReact":"99","screenV":"99","time":"95.86943"},{"spawnID":"116","spawnType":"Enemy","eventType":"Miss","eventCat":"Neutral","x":"3.45964622","y":"-25.16714","timeToReact":"99","screenV":"99","time":"96.0127945"},{"spawnID":"118","spawnType":"Obstacle","eventType":"Dodge","eventCat":"Neutral","x":"2.28302574","timeToReact":"99","screenV":"99","time":"96.5125961"},{"spawnID":"117","spawnType":"Bonus","eventType":"Miss","eventCat":"Neutral","x":"-7.62594652","timeToReact":"99","screenV":"99","time":"96.51435"},{"spawnID":"119","spawnType":"Bonus","eventType":"Miss","eventCat":"Neutral","x":"11.7037334","timeToReact":"99","screenV":"99","time":"97.60516"},{"spawnID":"124","spawnType":"Bonus","eventType":"Catch","eventCat":"Positive","x":"3.845333","timeToReact":"4.2495499","screenV":"6.68219","time":"97.7459946"},{"spawnID":"128","spawnType":"Enemy","eventType":"Hurt","eventCat":"Negative","x":"3.95608521","timeToReact":"3.2155253","screenV":"8.86865","time":"97.89313"},{"spawnID":"128","spawnType":"Enemy","eventType":"Hurt","eventCat":"Negative","x":"3.98442125","timeToReact":"3.3656006","screenV":"8.47319","time":"98.0432053"},{"spawnID":"128","spawnType":"Enemy","eventType":"Hurt","eventCat":"Negative","x":"3.99960923","timeToReact":"3.4400853","screenV":"8.28973","time":"98.11769"},{"spawnID":"128","spawnType":"Enemy","eventType":"Hurt","eventCat":"Negative","x":"4.02941465","timeToReact":"3.5912553","screenV":"7.94078","time":"98.26886"},{"spawnID":"128","spawnType":"Enemy","eventType":"Hurt","eventCat":"Negative","x":"4.04394865","timeToReact":"3.6676853","screenV":"7.77531","time":"98.34529"},{"spawnID":"126","spawnType":"Obstacle","eventType":"Collision","eventCat":"Negative","x":"5.00939369","timeToReact":"4.1749644","screenV":"5.98925","time":"98.57624"},{"spawnID":"121","spawnType":"Bonus","eventType":"Miss","eventCat":"Neutral","x":"10.2001591","timeToReact":"99","screenV":"99","time":"98.80833"},{"spawnID":"127","spawnType":"Bonus","eventType":"Catch","eventCat":"Positive","x":"3.366577","timeToReact":"4.43499","screenV":"6.57778","time":"99.03824"},{"spawnID":"122","spawnType":"Bonus","eventType":"Miss","eventCat":"Neutral","x":"-10.9624958","timeToReact":"99","screenV":"99","time":"99.81837"},{"spawnID":"123","spawnType":"Enemy","eventType":"Miss","eventCat":"Neutral","x":"-7.93273449","y":"-25.50797","timeToReact":"99","screenV":"99","time":"100.125465"},{"spawnID":"125","spawnType":"Obstacle","eventType":"Dodge","eventCat":"Neutral","x":"13.4276237","timeToReact":"99","screenV":"99","time":"100.636505"},{"spawnID":"128","spawnType":"Enemy","eventType":"Miss","eventCat":"Neutral","x":"9.089262","y":"-24.90294","timeToReact":"99","screenV":"99","time":"100.776848"},{"spawnID":"126","spawnType":"Obstacle","eventType":"Dodge","eventCat":"Neutral","x":"5.00939369","timeToReact":"99","screenV":"99","time":"101.045387"},{"spawnID":"133","spawnType":"Bonus","eventType":"Catch","eventCat":"Positive","x":"0.008832114","timeToReact":"4.5638051","screenV":"6.47005","time":"101.45575"},{"spawnID":"129","spawnType":"Obstacle","eventType":"Dodge","eventCat":"Neutral","x":"-8.667972","timeToReact":"99","screenV":"99","time":"101.7292"},{"spawnID":"131","spawnType":"Obstacle","eventType":"Dodge","eventCat":"Neutral","x":"15.7271309","timeToReact":"99","screenV":"99","time":"102.81675"},{"spawnID":"130","spawnType":"Bonus","eventType":"Miss","eventCat":"Neutral","x":"5.988152","timeToReact":"99","screenV":"99","time":"103.01799"},{"spawnID":"132","spawnType":"Enemy","eventType":"Miss","eventCat":"Neutral","x":"-14.0599747","y":"-25.20605","timeToReact":"99","screenV":"99","time":"104.150169"},{"spawnID":"138","spawnType":"Obstacle","eventType":"Collision","eventCat":"Negative","x":"-2.17192268","timeToReact":"4.402702","screenV":"6.04599","time":"104.846458"},{"spawnID":"134","spawnType":"Bonus","eventType":"Miss","eventCat":"Neutral","x":"-6.33542967","timeToReact":"99","screenV":"99","time":"105.20256"},{"spawnID":"141","spawnType":"Bonus","eventType":"Catch","eventCat":"Positive","x":"2.57362151","timeToReact":"5.203201","screenV":"5.90276","time":"106.474518"},{"spawnID":"136","spawnType":"Bonus","eventType":"Miss","eventCat":"Neutral","x":"-13.3281546","timeToReact":"99","screenV":"99","time":"106.8248"},{"spawnID":"139","spawnType":"Enemy","eventType":"Miss","eventCat":"Neutral","x":"9.882164","y":"-24.9534378","timeToReact":"99","screenV":"99","time":"106.964752"},{"spawnID":"138","spawnType":"Obstacle","eventType":"Dodge","eventCat":"Neutral","x":"-2.17192268","timeToReact":"99","screenV":"99","time":"107.174652"},{"spawnID":"140","spawnType":"Obstacle","eventType":"Dodge","eventCat":"Neutral","x":"15.2267342","timeToReact":"99","screenV":"99","time":"107.718575"},{"spawnID":"144","spawnType":"Bonus","eventType":"Catch","eventCat":"Positive","x":"3.08424616","timeToReact":"4.351242","screenV":"6.55919","time":"107.856857"},{"spawnID":"137","spawnType":"Bonus","eventType":"Miss","eventCat":"Neutral","x":"-9.636065","timeToReact":"99","screenV":"99","time":"107.857346"},{"spawnID":"148","spawnType":"Enemy","eventType":"Kill","eventCat":"Positive","x":"2.88759351","timeToReact":"3.253838","screenV":"4.70358","time":"108.190819"},{"spawnID":"148","spawnType":"Enemy","eventType":"Hit","eventCat":"Positive","x":"2.88759351","timeToReact":"3.253937","screenV":"4.70343","time":"108.190918"},{"spawnID":"145","spawnType":"Obstacle","eventType":"Collision","eventCat":"Negative","x":"4.40259","timeToReact":"4.279172","screenV":"5.97273","time":"108.929672"},{"spawnID":"142","spawnType":"Bonus","eventType":"Miss","eventCat":"Neutral","x":"9.048434","timeToReact":"99","screenV":"99","time":"109.912651"},{"spawnID":"149","spawnType":"Bonus","eventType":"Catch","eventCat":"Positive","x":"6.20354271","timeToReact":"4.502525","screenV":"6.43297","time":"110.324707"},{"spawnID":"143","spawnType":"Enemy","eventType":"Miss","eventCat":"Neutral","x":"11.1817551","y":"-25.0134926","timeToReact":"99","screenV":"99","time":"110.390442"},{"spawnID":"151","spawnType":"Enemy","eventType":"Kill","eventCat":"Positive","x":"3.349592","timeToReact":"3.624413","screenV":"4.93335","time":"110.724556"},{"spawnID":"151","spawnType":"Enemy","eventType":"Hit","eventCat":"Positive","x":"3.349592","timeToReact":"3.624466","screenV":"4.93327","time":"110.724609"},{"spawnID":"145","spawnType":"Obstacle","eventType":"Dodge","eventCat":"Neutral","x":"4.40259","timeToReact":"99","screenV":"99","time":"111.410545"},{"spawnID":"147","spawnType":"Obstacle","eventType":"Dodge","eventCat":"Neutral","x":"14.4501991","timeToReact":"99","screenV":"99","time":"111.535683"},{"spawnID":"150","spawnType":"Bonus","eventType":"Catch","eventCat":"Positive","x":"5.87102032","timeToReact":"4.553383","screenV":"6.61851","time":"111.536476"},{"spawnID":"146","spawnType":"Bonus","eventType":"Miss","eventCat":"Neutral","x":"10.2583055","timeToReact":"99","screenV":"99","time":"112.017006"},{"spawnID":"152","spawnType":"Bonus","eventType":"Catch","eventCat":"Positive","x":"6.20669746","timeToReact":"4.114929","screenV":"6.84935","time":"112.256233"},{"spawnID":"153","spawnType":"Enemy","eventType":"Kill","eventCat":"Positive","x":"4.37792253","timeToReact":"3.096878","screenV":"4.98865","time":"112.257652"},{"spawnID":"153","spawnType":"Enemy","eventType":"Hit","eventCat":"Positive","x":"4.37792253","timeToReact":"3.097199","screenV":"4.98813","time":"112.257973"},{"spawnID":"154","spawnType":"Bonus","eventType":"Miss","eventCat":"Neutral","x":"11.909708","timeToReact":"99","screenV":"99","time":"116.49572"}]