{"sessionID":"55b0ac5f2bf1bfe40f9f2477","patientId":"559252a9b75a5fbc1b3cf2f9","date":"2015-07-23 10:57:03","exerciseType":"HANDPOINT","exerciseDirection":"BOTH","nbRepetitions":"3","actionPhaseDuration":"30","restPhaseDuration":"10","score":"1360","performance":"0.34787314100542843","completed":"true","duration":"120.0228","logs":[{"spawnID":"2","spawnType":"Bonus","eventType":"Catch","eventCat":"Positive","x":"-10.6009874","timeToReact":"3.82689022","screenV":"7.38057","time":"5.391721"},{"spawnID":"8","spawnType":"Enemy","eventType":"Kill","eventCat":"Positive","x":"-4.29577875","timeToReact":"2.6574317","screenV":"5.62910","time":"6.0466547"},{"spawnID":"8","spawnType":"Enemy","eventType":"Hit","eventCat":"Positive","x":"-4.29577875","timeToReact":"2.658061","screenV":"5.62777","time":"6.047284"},{"spawnID":"4","spawnType":"Bonus","eventType":"Catch","eventCat":"Positive","x":"-4.20016","timeToReact":"4.096730","screenV":"7.28566","time":"6.261278"},{"spawnID":"6","spawnType":"Bonus","eventType":"Catch","eventCat":"Positive","x":"1.88237762","timeToReact":"4.20662846","screenV":"6.91775","time":"6.812009"},{"spawnID":"7","spawnType":"Bonus","eventType":"Catch","eventCat":"Positive","x":"3.21175361","timeToReact":"3.78463698","screenV":"7.13958","time":"6.86224747"},{"spawnID":"1","spawnType":"Obstacle","eventType":"Dodge","eventCat":"Neutral","x":"9.881462","timeToReact":"99","screenV":"99","time":"7.129591"},{"spawnID":"3","spawnType":"Obstacle","eventType":"Dodge","eventCat":"Neutral","x":"14.2865868","timeToReact":"99","screenV":"99","time":"7.76654434"},{"spawnID":"9","spawnType":"Bonus","eventType":"Catch","eventCat":"Positive","x":"-3.66972637","timeToReact":"4.28026486","screenV":"6.76539","time":"7.80079842"},{"spawnID":"16","spawnType":"Enemy","eventType":"Kill","eventCat":"Positive","x":"-3.90775418","timeToReact":"2.701573","screenV":"7.48247","time":"8.476137"},{"spawnID":"16","spawnType":"Enemy","eventType":"Hit","eventCat":"Positive","x":"-3.90775418","timeToReact":"2.701669","screenV":"7.48220","time":"8.476233"},{"spawnID":"12","spawnType":"Bonus","eventType":"Catch","eventCat":"Positive","x":"-0.773693562","timeToReact":"4.227245","screenV":"6.51160","time":"8.642549"},{"spawnID":"10","spawnType":"Bonus","eventType":"Catch","eventCat":"Positive","x":"2.298604","timeToReact":"4.901125","screenV":"5.82111","time":"8.874899"},{"spawnID":"14","spawnType":"Bonus","eventType":"Catch","eventCat":"Positive","x":"9.245493","timeToReact":"4.30955375","screenV":"6.33759","time":"9.188707"},{"spawnID":"15","spawnType":"Bonus","eventType":"Catch","eventCat":"Positive","x":"4.141531","timeToReact":"4.49671375","screenV":"6.29600","time":"9.903782"},{"spawnID":"23","spawnType":"Enemy","eventType":"Kill","eventCat":"Positive","x":"5.06678247","timeToReact":"2.3801178","screenV":"6.76879","time":"10.8500748"},{"spawnID":"23","spawnType":"Enemy","eventType":"Hit","eventCat":"Positive","x":"5.06678247","timeToReact":"2.3803667","screenV":"6.76808","time":"10.8503237"},{"spawnID":"17","spawnType":"Bonus","eventType":"Catch","eventCat":"Positive","x":"10.378129","timeToReact":"4.890276","screenV":"5.88637","time":"10.85034"},{"spawnID":"18","spawnType":"Bonus","eventType":"Catch","eventCat":"Positive","x":"9.53093052","timeToReact":"4.3795192","screenV":"6.14401","time":"10.8657722"},{"spawnID":"11","spawnType":"Obstacle","eventType":"Dodge","eventCat":"Neutral","x":"-12.3033447","timeToReact":"99","screenV":"99","time":"11.0286846"},{"spawnID":"19","spawnType":"Bonus","eventType":"Catch","eventCat":"Positive","x":"1.37912929","timeToReact":"4.7324313","screenV":"6.15845","time":"11.7395573"},{"spawnID":"21","spawnType":"Bonus","eventType":"Catch","eventCat":"Positive","x":"-4.270069","timeToReact":"4.6279135","screenV":"6.34844","time":"12.1678982"},{"spawnID":"22","spawnType":"Bonus","eventType":"Catch","eventCat":"Positive","x":"5.78357744","timeToReact":"4.8116213","screenV":"6.04427","time":"12.8874493"},{"spawnID":"24","spawnType":"Bonus","eventType":"Catch","eventCat":"Positive","x":"-9.965829","timeToReact":"5.6398531","screenV":"5.05891","time":"14.2929211"},{"spawnID":"28","spawnType":"Enemy","eventType":"Kill","eventCat":"Positive","x":"0.234151721","timeToReact":"4.48182","screenV":"4.23426","time":"14.46126"},{"spawnID":"28","spawnType":"Enemy","eventType":"Hit","eventCat":"Positive","x":"0.234151721","timeToReact":"4.4819171","screenV":"4.23417","time":"14.4613571"},{"spawnID":"13","spawnType":"Enemy","eventType":"Miss","eventCat":"Neutral","x":"-14.6576948","y":"-24.7151051","timeToReact":"99","screenV":"99","time":"14.5280361"},{"spawnID":"29","spawnType":"Bonus","eventType":"Catch","eventCat":"Positive","x":"-3.18133259","timeToReact":"4.5601320","screenV":"6.10672","time":"15.0402107"},{"spawnID":"26","spawnType":"Obstacle","eventType":"Collision","eventCat":"Negative","x":"1.43205833","timeToReact":"5.547479","screenV":"5.49302","time":"15.089695"},{"spawnID":"32","spawnType":"Enemy","eventType":"Kill","eventCat":"Positive","x":"-14.0740776","timeToReact":"3.6264944","screenV":"5.55228","time":"15.1835556"},{"spawnID":"32","spawnType":"Enemy","eventType":"Hit","eventCat":"Positive","x":"-14.0740776","timeToReact":"3.6265135","screenV":"5.55226","time":"15.1835747"},{"spawnID":"20","spawnType":"Enemy","eventType":"Miss","eventCat":"Neutral","x":"-15.3481865","y":"-25.07308","timeToReact":"99","screenV":"99","time":"15.2645969"},{"spawnID":"36","spawnType":"Enemy","eventType":"Hit","eventCat":"Positive","x":"-5.62124538","timeToReact":"2.8235759","screenV":"5.40855","time":"15.9008617"},{"spawnID":"31","spawnType":"Bonus","eventType":"Catch","eventCat":"Positive","x":"-4.43286","timeToReact":"5.1407814","screenV":"5.50123","time":"16.2863846"},{"spawnID":"33","spawnType":"Bonus","eventType":"Catch","eventCat":"Positive","x":"-6.09939766","timeToReact":"4.6782589","screenV":"5.93285","time":"16.4687977"},{"spawnID":"34","spawnType":"Bonus","eventType":"Catch","eventCat":"Positive","x":"-6.1251297","timeToReact":"4.1965999","screenV":"6.19948","time":"16.5741062"},{"spawnID":"36","spawnType":"Enemy","eventType":"Kill","eventCat":"Positive","x":"-5.62124538","timeToReact":"3.7648887","screenV":"5.50816","time":"16.8421745"},{"spawnID":"36","spawnType":"Enemy","eventType":"Hit","eventCat":"Positive","x":"-5.62124538","timeToReact":"3.7649212","screenV":"5.50811","time":"16.842207"},{"spawnID":"26","spawnType":"Obstacle","eventType":"Dodge","eventCat":"Neutral","x":"1.43205833","timeToReact":"99","screenV":"99","time":"16.9890213"},{"spawnID":"35","spawnType":"Bonus","eventType":"Catch","eventCat":"Positive","x":"4.06472731","timeToReact":"4.4559574","screenV":"6.16671","time":"17.4628315"},{"spawnID":"25","spawnType":"Bonus","eventType":"Miss","eventCat":"Neutral","x":"11.993041","timeToReact":"99","screenV":"99","time":"17.61117"},{"spawnID":"30","spawnType":"Obstacle","eventType":"Dodge","eventCat":"Neutral","x":"-6.748214","timeToReact":"99","screenV":"99","time":"17.9697227"},{"spawnID":"27","spawnType":"Bonus","eventType":"Miss","eventCat":"Neutral","x":"12.1346235","timeToReact":"99","screenV":"99","time":"18.2761116"},{"spawnID":"38","spawnType":"Bonus","eventType":"Catch","eventCat":"Positive","x":"9.484872","timeToReact":"4.4717607","screenV":"6.27165","time":"18.68122"},{"spawnID":"59","spawnType":"Bonus","eventType":"Miss","eventCat":"Neutral","x":"-14.085969","timeToReact":"99","screenV":"99","time":"19.2631683"},{"spawnID":"60","spawnType":"Bonus","eventType":"Miss","eventCat":"Neutral","x":"-15.0980349","timeToReact":"99","screenV":"99","time":"19.3971176"},{"spawnID":"41","spawnType":"Bonus","eventType":"Catch","eventCat":"Positive","x":"-5.052439","timeToReact":"4.6496093","screenV":"6.01004","time":"19.42928"},{"spawnID":"37","spawnType":"Bonus","eventType":"Catch","eventCat":"Positive","x":"-5.78081274","timeToReact":"5.8483677","screenV":"5.10559","time":"19.4633522"},{"spawnID":"56","spawnType":"Bonus","eventType":"Miss","eventCat":"Neutral","x":"-14.1580629","timeToReact":"99","screenV":"99","time":"19.5243053"},{"spawnID":"55","spawnType":"Bonus","eventType":"Miss","eventCat":"Neutral","x":"-13.9422674","timeToReact":"99","screenV":"99","time":"19.58928"},{"spawnID":"57","spawnType":"Bonus","eventType":"Miss","eventCat":"Neutral","x":"-13.8150129","timeToReact":"99","screenV":"99","time":"19.5892944"},{"spawnID":"61","spawnType":"Bonus","eventType":"Miss","eventCat":"Neutral","x":"-14.7444038","timeToReact":"99","screenV":"99","time":"19.5893021"},{"spawnID":"62","spawnType":"Bonus","eventType":"Miss","eventCat":"Neutral","x":"-14.1858091","timeToReact":"99","screenV":"99","time":"19.6051922"},{"spawnID":"53","spawnType":"Bonus","eventType":"Miss","eventCat":"Neutral","x":"-13.6826925","timeToReact":"99","screenV":"99","time":"19.63925"},{"spawnID":"54","spawnType":"Bonus","eventType":"Miss","eventCat":"Neutral","x":"-14.6438665","timeToReact":"99","screenV":"99","time":"19.658556"},{"spawnID":"58","spawnType":"Bonus","eventType":"Miss","eventCat":"Neutral","x":"-15.39578","timeToReact":"99","screenV":"99","time":"19.7901573"},{"spawnID":"42","spawnType":"Bonus","eventType":"Catch","eventCat":"Positive","x":"-9.841216","timeToReact":"4.3851452","screenV":"6.45464","time":"19.8248024"},{"spawnID":"52","spawnType":"Bonus","eventType":"Miss","eventCat":"Neutral","x":"-13.9832544","timeToReact":"99","screenV":"99","time":"19.85693"},{"spawnID":"39","spawnType":"Enemy","eventType":"Miss","eventCat":"Neutral","x":"-9.204348","y":"-24.8834324","timeToReact":"99","screenV":"99","time":"21.10495"},{"spawnID":"46","spawnType":"Bonus","eventType":"Catch","eventCat":"Positive","x":"-11.962018","timeToReact":"4.3867419","screenV":"6.34376","time":"21.1049919"},{"spawnID":"49","spawnType":"Bonus","eventType":"Catch","eventCat":"Positive","x":"1.14162946","timeToReact":"4.5950318","screenV":"5.97225","time":"21.8918648"},{"spawnID":"40","spawnType":"Obstacle","eventType":"Dodge","eventCat":"Neutral","x":"2.38749123","timeToReact":"99","screenV":"99","time":"22.0248337"},{"spawnID":"48","spawnType":"Obstacle","eventType":"Collision","eventCat":"Negative","x":"6.097166","timeToReact":"5.1784382","screenV":"5.72288","time":"22.0599213"},{"spawnID":"50","spawnType":"Enemy","eventType":"Kill","eventCat":"Positive","x":"6.459765","timeToReact":"5.0159954","screenV":"4.34108","time":"22.62789"},{"spawnID":"50","spawnType":"Enemy","eventType":"Hit","eventCat":"Positive","x":"6.459765","timeToReact":"5.0160198","screenV":"4.34106","time":"22.6279144"},{"spawnID":"65","spawnType":"Enemy","eventType":"Hurt","eventCat":"Negative","x":"11.51777","timeToReact":"3.7243764","screenV":"7.63973","time":"22.7951164"},{"spawnID":"65","spawnType":"Enemy","eventType":"Hurt","eventCat":"Negative","x":"11.8406324","timeToReact":"3.7740171","screenV":"7.53925","time":"22.8447571"},{"spawnID":"65","spawnType":"Enemy","eventType":"Hurt","eventCat":"Negative","x":"11.9852371","timeToReact":"3.7926881","screenV":"7.50213","time":"22.8634281"},{"spawnID":"51","spawnType":"Bonus","eventType":"Catch","eventCat":"Positive","x":"12.1965818","timeToReact":"4.996862","screenV":"5.70543","time":"22.89529"},{"spawnID":"65","spawnType":"Enemy","eventType":"Hurt","eventCat":"Negative","x":"12.0593891","timeToReact":"3.8590276","screenV":"7.37316","time":"22.9297676"},{"spawnID":"65","spawnType":"Enemy","eventType":"Hurt","eventCat":"Negative","x":"11.8814621","timeToReact":"3.909517","screenV":"7.27794","time":"22.980257"},{"spawnID":"43","spawnType":"Obstacle","eventType":"Dodge","eventCat":"Neutral","x":"-5.659278","timeToReact":"99","screenV":"99","time":"23.06228"},{"spawnID":"65","spawnType":"Enemy","eventType":"Hit","eventCat":"Positive","x":"13.6958466","timeToReact":"4.1941831","screenV":"5.49116","time":"23.2649231"},{"spawnID":"66","spawnType":"Bonus","eventType":"Catch","eventCat":"Positive","x":"-7.896157","timeToReact":"4.9749051","screenV":"5.68207","time":"24.0460835"},{"spawnID":"47","spawnType":"Obstacle","eventType":"Dodge","eventCat":"Neutral","x":"6.223913","timeToReact":"99","screenV":"99","time":"24.1286469"},{"spawnID":"44","spawnType":"Bonus","eventType":"Miss","eventCat":"Neutral","x":"3.34505653","timeToReact":"99","screenV":"99","time":"24.1292114"},{"spawnID":"48","spawnType":"Obstacle","eventType":"Dodge","eventCat":"Neutral","x":"6.097166","timeToReact":"99","screenV":"99","time":"24.1616383"},{"spawnID":"69","spawnType":"Bonus","eventType":"Catch","eventCat":"Positive","x":"-11.1183987","timeToReact":"4.5524101","screenV":"6.09303","time":"24.7584457"},{"spawnID":"74","spawnType":"Bonus","eventType":"Catch","eventCat":"Positive","x":"-9.055821","timeToReact":"4.1054230","screenV":"5.89624","time":"25.4696369"},{"spawnID":"63","spawnType":"Obstacle","eventType":"Dodge","eventCat":"Neutral","x":"-15.6958961","timeToReact":"99","screenV":"99","time":"25.55255"},{"spawnID":"72","spawnType":"Bonus","eventType":"Catch","eventCat":"Positive","x":"-0.5408673","timeToReact":"5.2874532","screenV":"5.54154","time":"26.06424"},{"spawnID":"64","spawnType":"Bonus","eventType":"Miss","eventCat":"Neutral","x":"-13.3942423","timeToReact":"99","screenV":"99","time":"26.2837372"},{"spawnID":"77","spawnType":"Bonus","eventType":"Catch","eventCat":"Positive","x":"3.813743","timeToReact":"4.3757401","screenV":"6.33737","time":"26.4115849"},{"spawnID":"82","spawnType":"Enemy","eventType":"Kill","eventCat":"Positive","x":"-7.1656","timeToReact":"3.321025","screenV":"4.54112","time":"26.9234"},{"spawnID":"82","spawnType":"Enemy","eventType":"Hit","eventCat":"Positive","x":"-7.1656","timeToReact":"3.3210526","screenV":"4.54109","time":"26.9234276"},{"spawnID":"78","spawnType":"Bonus","eventType":"Catch","eventCat":"Positive","x":"3.794658","timeToReact":"4.3608761","screenV":"6.46054","time":"27.0972271"},{"spawnID":"68","spawnType":"Obstacle","eventType":"Dodge","eventCat":"Neutral","x":"-6.215314","timeToReact":"99","screenV":"99","time":"27.19687"},{"spawnID":"65","spawnType":"Enemy","eventType":"Miss","eventCat":"Neutral","x":"13.6958466","y":"-25.14759","timeToReact":"99","screenV":"99","time":"27.19742"},{"spawnID":"67","spawnType":"Bonus","eventType":"Miss","eventCat":"Neutral","x":"-2.84458661","timeToReact":"99","screenV":"99","time":"27.6868763"},{"spawnID":"81","spawnType":"Bonus","eventType":"Catch","eventCat":"Positive","x":"0.654657","timeToReact":"4.3944953","screenV":"6.18887","time":"27.78809"},{"spawnID":"71","spawnType":"Obstacle","eventType":"Dodge","eventCat":"Neutral","x":"5.66756248","timeToReact":"99","screenV":"99","time":"28.01875"},{"spawnID":"84","spawnType":"Bonus","eventType":"Catch","eventCat":"Positive","x":"3.43230963","timeToReact":"4.3239155","screenV":"6.21993","time":"28.2987518"},{"spawnID":"73","spawnType":"Obstacle","eventType":"Dodge","eventCat":"Neutral","x":"14.1660614","timeToReact":"99","screenV":"99","time":"28.5398979"},{"spawnID":"70","spawnType":"Enemy","eventType":"Miss","eventCat":"Neutral","x":"13.9902773","y":"-24.9193459","timeToReact":"99","screenV":"99","time":"28.8768959"},{"spawnID":"75","spawnType":"Obstacle","eventType":"Dodge","eventCat":"Neutral","x":"13.9565773","timeToReact":"99","screenV":"99","time":"28.8923874"},{"spawnID":"89","spawnType":"Bonus","eventType":"Catch","eventCat":"Positive","x":"5.022477","timeToReact":"4.29590","screenV":"6.33557","time":"29.40623"},{"spawnID":"79","spawnType":"Obstacle","eventType":"Dodge","eventCat":"Neutral","x":"-14.2832375","timeToReact":"99","screenV":"99","time":"29.9932022"},{"spawnID":"76","spawnType":"Enemy","eventType":"Miss","eventCat":"Neutral","x":"12.2257042","y":"-25.0519371","timeToReact":"99","screenV":"99","time":"29.99379"},{"spawnID":"80","spawnType":"Obstacle","eventType":"Dodge","eventCat":"Neutral","x":"-11.442688","timeToReact":"99","screenV":"99","time":"30.2266464"},{"spawnID":"90","spawnType":"Bonus","eventType":"Catch","eventCat":"Positive","x":"-0.770365655","timeToReact":"4.8672276","screenV":"5.85215","time":"30.5441628"},{"spawnID":"83","spawnType":"Obstacle","eventType":"Dodge","eventCat":"Neutral","x":"-1.83579063","timeToReact":"99","screenV":"99","time":"30.8281364"},{"spawnID":"85","spawnType":"Obstacle","eventType":"Dodge","eventCat":"Neutral","x":"8.516066","timeToReact":"99","screenV":"99","time":"31.1710472"},{"spawnID":"96","spawnType":"Enemy","eventType":"Hit","eventCat":"Positive","x":"-3.73665428","timeToReact":"3.4330249","screenV":"5.82006","time":"31.36412"},{"spawnID":"91","spawnType":"Bonus","eventType":"Catch","eventCat":"Positive","x":"6.05828428","timeToReact":"5.17302","screenV":"5.77824","time":"31.44843"},{"spawnID":"96","spawnType":"Enemy","eventType":"Kill","eventCat":"Positive","x":"-3.73665428","timeToReact":"3.6332016","screenV":"5.76880","time":"31.5642967"},{"spawnID":"96","spawnType":"Enemy","eventType":"Hit","eventCat":"Positive","x":"-3.73665428","timeToReact":"3.6333649","screenV":"5.76854","time":"31.56446"},{"spawnID":"93","spawnType":"Bonus","eventType":"Catch","eventCat":"Positive","x":"8.570749","timeToReact":"4.7741280","screenV":"6.16636","time":"31.6645966"},{"spawnID":"87","spawnType":"Obstacle","eventType":"Dodge","eventCat":"Neutral","x":"-10.5582962","timeToReact":"99","screenV":"99","time":"31.99543"},{"spawnID":"86","spawnType":"Bonus","eventType":"Miss","eventCat":"Neutral","x":"-9.487329","timeToReact":"99","screenV":"99","time":"32.4367867"},{"spawnID":"97","spawnType":"Bonus","eventType":"Catch","eventCat":"Positive","x":"-5.32724142","timeToReact":"4.7455718","screenV":"5.85009","time":"32.80325"},{"spawnID":"100","spawnType":"Enemy","eventType":"Hurt","eventCat":"Negative","x":"-5.60732269","timeToReact":"3.5217987","screenV":"8.07918","time":"32.87005"},{"spawnID":"100","spawnType":"Enemy","eventType":"Hurt","eventCat":"Negative","x":"-5.60732269","timeToReact":"3.5219387","screenV":"8.07886","time":"32.87019"},{"spawnID":"100","spawnType":"Enemy","eventType":"Hurt","eventCat":"Negative","x":"-5.60732269","timeToReact":"3.5219727","screenV":"8.07878","time":"32.870224"},{"spawnID":"100","spawnType":"Enemy","eventType":"Hurt","eventCat":"Negative","x":"-5.60732269","timeToReact":"3.5220147","screenV":"8.07868","time":"32.870266"},{"spawnID":"100","spawnType":"Enemy","eventType":"Hurt","eventCat":"Negative","x":"-5.60732269","timeToReact":"3.5220487","screenV":"8.07861","time":"32.8703"},{"spawnID":"100","spawnType":"Enemy","eventType":"Hurt","eventCat":"Negative","x":"-5.60732269","timeToReact":"3.5220787","screenV":"8.07854","time":"32.87033"},{"spawnID":"100","spawnType":"Enemy","eventType":"Hurt","eventCat":"Negative","x":"-6.00299072","timeToReact":"3.5597420","screenV":"7.99306","time":"32.9079933"},{"spawnID":"100","spawnType":"Enemy","eventType":"Hurt","eventCat":"Negative","x":"-6.466711","timeToReact":"3.5883287","screenV":"7.92939","time":"32.93658"},{"spawnID":"100","spawnType":"Enemy","eventType":"Kill","eventCat":"Positive","x":"-4.36281157","timeToReact":"3.5887587","screenV":"6.80876","time":"32.93701"},{"spawnID":"100","spawnType":"Enemy","eventType":"Hit","eventCat":"Positive","x":"-4.36281157","timeToReact":"3.5887833","screenV":"6.80871","time":"32.9370346"},{"spawnID":"100","spawnType":"Enemy","eventType":"Hurt","eventCat":"Negative","x":"-7.18697","timeToReact":"3.6553040","screenV":"7.78410","time":"33.0035553"},{"spawnID":"88","spawnType":"Enemy","eventType":"Miss","eventCat":"Neutral","x":"-6.621867","y":"-25.1726551","timeToReact":"99","screenV":"99","time":"33.03989"},{"spawnID":"100","spawnType":"Enemy","eventType":"Hurt","eventCat":"Negative","x":"-8.097486","timeToReact":"3.7603722","screenV":"7.56660","time":"33.1086235"},{"spawnID":"100","spawnType":"Enemy","eventType":"Hurt","eventCat":"Negative","x":"-8.413586","timeToReact":"3.7890664","screenV":"7.50930","time":"33.1373177"},{"spawnID":"95","spawnType":"Bonus","eventType":"Catch","eventCat":"Positive","x":"-9.010322","timeToReact":"5.7402426","screenV":"5.14149","time":"33.22321"},{"spawnID":"98","spawnType":"Bonus","eventType":"Catch","eventCat":"Positive","x":"-8.513912","timeToReact":"4.6687088","screenV":"6.21356","time":"33.3058929"},{"spawnID":"99","spawnType":"Bonus","eventType":"Catch","eventCat":"Positive","x":"-3.751664","timeToReact":"4.6812591","screenV":"5.92200","time":"33.8984222"},{"spawnID":"94","spawnType":"Obstacle","eventType":"Dodge","eventCat":"Neutral","x":"-6.56561565","timeToReact":"99","screenV":"99","time":"34.04025"},{"spawnID":"103","spawnType":"Bonus","eventType":"Catch","eventCat":"Positive","x":"0.9260263","timeToReact":"4.4435730","screenV":"6.44148","time":"34.2418442"},{"spawnID":"92","spawnType":"Enemy","eventType":"Miss","eventCat":"Neutral","x":"-15.5935555","y":"-25.0481567","timeToReact":"99","screenV":"99","time":"34.40149"},{"spawnID":"101","spawnType":"Obstacle","eventType":"Dodge","eventCat":"Neutral","x":"-10.99757","timeToReact":"99","screenV":"99","time":"36.1996346"},{"spawnID":"102","spawnType":"Obstacle","eventType":"Dodge","eventCat":"Neutral","x":"-13.2112617","timeToReact":"99","screenV":"99","time":"36.48354"},{"spawnID":"104","spawnType":"Obstacle","eventType":"Dodge","eventCat":"Neutral","x":"8.465755","timeToReact":"99","screenV":"99","time":"36.58383"},{"spawnID":"105","spawnType":"Bonus","eventType":"Catch","eventCat":"Positive","x":"5.04951334","timeToReact":"3.4224015","screenV":"7.73765","time":"43.8639374"},{"spawnID":"106","spawnType":"Bonus","eventType":"Catch","eventCat":"Positive","x":"-10.5163841","timeToReact":"4.2703591","screenV":"6.45561","time":"45.144825"},{"spawnID":"108","spawnType":"Bonus","eventType":"Catch","eventCat":"Positive","x":"-0.6482429","timeToReact":"4.4170418","screenV":"6.62652","time":"45.7242851"},{"spawnID":"112","spawnType":"Enemy","eventType":"Kill","eventCat":"Positive","x":"-11.2264957","timeToReact":"3.7259768","screenV":"5.00495","time":"45.89023"},{"spawnID":"112","spawnType":"Enemy","eventType":"Hit","eventCat":"Positive","x":"-11.2264957","timeToReact":"3.7260868","screenV":"5.00480","time":"45.89034"},{"spawnID":"110","spawnType":"Bonus","eventType":"Catch","eventCat":"Positive","x":"10.06708","timeToReact":"4.5359867","screenV":"6.31727","time":"46.2777367"},{"spawnID":"113","spawnType":"Bonus","eventType":"Catch","eventCat":"Positive","x":"8.83879852","timeToReact":"4.1662429","screenV":"6.91584","time":"46.35866"},{"spawnID":"111","spawnType":"Obstacle","eventType":"Collision","eventCat":"Negative","x":"14.8936176","timeToReact":"4.6274910","screenV":"6.21700","time":"46.5597763"},{"spawnID":"118","spawnType":"Enemy","eventType":"Kill","eventCat":"Positive","x":"-0.0667559654","timeToReact":"3.4402885","screenV":"4.69275","time":"46.8439941"},{"spawnID":"118","spawnType":"Enemy","eventType":"Hit","eventCat":"Positive","x":"-0.0667559654","timeToReact":"3.4403244","screenV":"4.69270","time":"46.84403"},{"spawnID":"116","spawnType":"Bonus","eventType":"Catch","eventCat":"Positive","x":"11.4099426","timeToReact":"4.2195829","screenV":"6.66993","time":"46.8627129"},{"spawnID":"107","spawnType":"Enemy","eventType":"Miss","eventCat":"Neutral","x":"-19.0683384","y":"-24.85612","timeToReact":"99","screenV":"99","time":"46.96077"},{"spawnID":"114","spawnType":"Obstacle","eventType":"Collision","eventCat":"Negative","x":"6.426066","timeToReact":"4.6778345","screenV":"6.04767","time":"47.1114845"},{"spawnID":"122","spawnType":"Enemy","eventType":"Hit","eventCat":"Positive","x":"8.180206","timeToReact":"2.6151428","screenV":"5.89639","time":"47.3979149"},{"spawnID":"122","spawnType":"Enemy","eventType":"Kill","eventCat":"Positive","x":"8.180206","timeToReact":"2.8127279","screenV":"5.87518","time":"47.5955"},{"spawnID":"122","spawnType":"Enemy","eventType":"Hit","eventCat":"Positive","x":"8.180206","timeToReact":"2.8127579","screenV":"5.87512","time":"47.59553"},{"spawnID":"117","spawnType":"Bonus","eventType":"Catch","eventCat":"Positive","x":"0.598855257","timeToReact":"4.569243","screenV":"6.08552","time":"47.731823"},{"spawnID":"119","spawnType":"Bonus","eventType":"Catch","eventCat":"Positive","x":"1.58675039","timeToReact":"4.3192736","screenV":"6.45399","time":"48.06523"},{"spawnID":"109","spawnType":"Obstacle","eventType":"Dodge","eventCat":"Neutral","x":"-7.078231","timeToReact":"99","screenV":"99","time":"48.2819939"},{"spawnID":"121","spawnType":"Bonus","eventType":"Catch","eventCat":"Positive","x":"4.253685","timeToReact":"4.2441215","screenV":"6.71632","time":"48.5478363"},{"spawnID":"111","spawnType":"Obstacle","eventType":"Dodge","eventCat":"Neutral","x":"14.8936176","timeToReact":"99","screenV":"99","time":"48.70638"},{"spawnID":"126","spawnType":"Enemy","eventType":"Kill","eventCat":"Positive","x":"1.897395","timeToReact":"2.4652023","screenV":"7.23460","time":"48.7073555"},{"spawnID":"126","spawnType":"Enemy","eventType":"Hit","eventCat":"Positive","x":"1.897395","timeToReact":"2.4652268","screenV":"7.23452","time":"48.70738"},{"spawnID":"123","spawnType":"Bonus","eventType":"Catch","eventCat":"Positive","x":"-2.72150588","timeToReact":"4.2965938","screenV":"6.57086","time":"49.16982"},{"spawnID":"115","spawnType":"Obstacle","eventType":"Dodge","eventCat":"Neutral","x":"-9.16846752","timeToReact":"99","screenV":"99","time":"49.2559433"},{"spawnID":"114","spawnType":"Obstacle","eventType":"Dodge","eventCat":"Neutral","x":"6.426066","timeToReact":"99","screenV":"99","time":"49.4124527"},{"spawnID":"126","spawnType":"Enemy","eventType":"Hurt","eventCat":"Negative","x":"-4.15576935","timeToReact":"3.2051968","screenV":"8.87722","time":"49.44735"},{"spawnID":"126","spawnType":"Enemy","eventType":"Hurt","eventCat":"Negative","x":"-4.15576935","timeToReact":"3.2052688","screenV":"8.87702","time":"49.447422"},{"spawnID":"126","spawnType":"Enemy","eventType":"Hurt","eventCat":"Negative","x":"-4.02739","timeToReact":"3.2201500","screenV":"8.83600","time":"49.4623032"},{"spawnID":"124","spawnType":"Bonus","eventType":"Catch","eventCat":"Positive","x":"4.849498","timeToReact":"4.540329","screenV":"6.26844","time":"49.990715"},{"spawnID":"125","spawnType":"Bonus","eventType":"Catch","eventCat":"Positive","x":"2.1748035","timeToReact":"4.450784","screenV":"6.21095","time":"50.48504"},{"spawnID":"131","spawnType":"Enemy","eventType":"Hit","eventCat":"Positive","x":"6.23177147","timeToReact":"3.0913132","screenV":"5.97563","time":"50.7277832"},{"spawnID":"120","spawnType":"Obstacle","eventType":"Dodge","eventCat":"Neutral","x":"-15.1157646","timeToReact":"99","screenV":"99","time":"50.82424"},{"spawnID":"131","spawnType":"Enemy","eventType":"Kill","eventCat":"Positive","x":"6.23177147","timeToReact":"3.18856","screenV":"5.94884","time":"50.82503"},{"spawnID":"131","spawnType":"Enemy","eventType":"Hit","eventCat":"Positive","x":"6.23177147","timeToReact":"3.1885842","screenV":"5.94880","time":"50.8250542"},{"spawnID":"127","spawnType":"Bonus","eventType":"Catch","eventCat":"Positive","x":"-2.72823071","timeToReact":"4.3488999","screenV":"6.53607","time":"50.9659157"},{"spawnID":"128","spawnType":"Bonus","eventType":"Catch","eventCat":"Positive","x":"-0.870994568","timeToReact":"4.1652679","screenV":"6.53279","time":"51.347435"},{"spawnID":"132","spawnType":"Bonus","eventType":"Catch","eventCat":"Positive","x":"0.1487568","timeToReact":"4.1385225","screenV":"6.63136","time":"51.91056"},{"spawnID":"134","spawnType":"Bonus","eventType":"Catch","eventCat":"Positive","x":"-0.391567022","timeToReact":"3.9731484","screenV":"6.52455","time":"52.302063"},{"spawnID":"135","spawnType":"Bonus","eventType":"Catch","eventCat":"Positive","x":"-4.480428","timeToReact":"4.4871134","screenV":"6.37998","time":"53.4066734"},{"spawnID":"129","spawnType":"Obstacle","eventType":"Dodge","eventCat":"Neutral","x":"-8.183452","timeToReact":"99","screenV":"99","time":"54.08884"},{"spawnID":"137","spawnType":"Bonus","eventType":"Catch","eventCat":"Positive","x":"-11.5744343","timeToReact":"4.7591209","screenV":"6.00771","time":"54.2218475"},{"spawnID":"130","spawnType":"Obstacle","eventType":"Dodge","eventCat":"Neutral","x":"-3.43272972","timeToReact":"99","screenV":"99","time":"54.45827"},{"spawnID":"138","spawnType":"Bonus","eventType":"Catch","eventCat":"Positive","x":"1.86917627","timeToReact":"5.0818558","screenV":"5.56373","time":"55.1145134"},{"spawnID":"133","spawnType":"Obstacle","eventType":"Dodge","eventCat":"Neutral","x":"-13.693924","timeToReact":"99","screenV":"99","time":"55.2294655"},{"spawnID":"140","spawnType":"Bonus","eventType":"Catch","eventCat":"Positive","x":"6.74526739","timeToReact":"4.77784","screenV":"5.62446","time":"55.37886"},{"spawnID":"141","spawnType":"Bonus","eventType":"Catch","eventCat":"Positive","x":"10.3345747","timeToReact":"4.4487572","screenV":"6.30861","time":"55.6131935"},{"spawnID":"139","spawnType":"Enemy","eventType":"Hurt","eventCat":"Negative","x":"13.7321024","timeToReact":"5.67397","screenV":"5.01470","time":"56.10304"},{"spawnID":"139","spawnType":"Enemy","eventType":"Hurt","eventCat":"Negative","x":"13.7006273","timeToReact":"5.690948","screenV":"4.99974","time":"56.120018"},{"spawnID":"139","spawnType":"Enemy","eventType":"Hurt","eventCat":"Negative","x":"13.5845251","timeToReact":"5.7274127","screenV":"4.96790","time":"56.1564827"},{"spawnID":"139","spawnType":"Enemy","eventType":"Hurt","eventCat":"Negative","x":"13.3580256","timeToReact":"5.7580752","screenV":"4.94145","time":"56.1871452"},{"spawnID":"139","spawnType":"Enemy","eventType":"Hurt","eventCat":"Negative","x":"10.7830553","timeToReact":"5.9581637","screenV":"4.77550","time":"56.3872337"},{"spawnID":"142","spawnType":"Obstacle","eventType":"Collision","eventCat":"Negative","x":"6.358885","timeToReact":"4.8997803","screenV":"5.79652","time":"56.469677"},{"spawnID":"145","spawnType":"Obstacle","eventType":"Collision","eventCat":"Negative","x":"3.40811729","timeToReact":"4.4508667","screenV":"5.77673","time":"56.6880035"},{"spawnID":"136","spawnType":"Enemy","eventType":"Miss","eventCat":"Neutral","x":"15.8742294","y":"-25.0087242","timeToReact":"99","screenV":"99","time":"56.78988"},{"spawnID":"146","spawnType":"Bonus","eventType":"Catch","eventCat":"Positive","x":"0.211866915","timeToReact":"4.5975456","screenV":"5.90728","time":"56.8863525"},{"spawnID":"147","spawnType":"Bonus","eventType":"Catch","eventCat":"Positive","x":"-4.50796366","timeToReact":"4.3816062","screenV":"6.44565","time":"57.2373"},{"spawnID":"143","spawnType":"Bonus","eventType":"Catch","eventCat":"Positive","x":"-5.493903","timeToReact":"5.5431786","screenV":"5.16702","time":"57.2735558"},{"spawnID":"149","spawnType":"Bonus","eventType":"Catch","eventCat":"Positive","x":"-5.920781","timeToReact":"4.5194751","screenV":"6.12070","time":"57.9598351"},{"spawnID":"152","spawnType":"Bonus","eventType":"Catch","eventCat":"Positive","x":"4.9669795","timeToReact":"4.4848404","screenV":"6.14045","time":"58.5252228"},{"spawnID":"142","spawnType":"Obstacle","eventType":"Dodge","eventCat":"Neutral","x":"6.358885","timeToReact":"99","screenV":"99","time":"58.64538"},{"spawnID":"154","spawnType":"Bonus","eventType":"Catch","eventCat":"Positive","x":"10.5697842","timeToReact":"4.3913498","screenV":"6.52475","time":"59.0187721"},{"spawnID":"145","spawnType":"Obstacle","eventType":"Dodge","eventCat":"Neutral","x":"3.40811729","timeToReact":"99","screenV":"99","time":"59.25805"},{"spawnID":"155","spawnType":"Enemy","eventType":"Kill","eventCat":"Positive","x":"11.7214842","timeToReact":"4.81164","screenV":"4.59633","time":"59.54938"},{"spawnID":"155","spawnType":"Enemy","eventType":"Hit","eventCat":"Positive","x":"11.7214842","timeToReact":"4.81167","screenV":"4.59631","time":"59.54941"},{"spawnID":"144","spawnType":"Enemy","eventType":"Miss","eventCat":"Neutral","x":"-15.9830589","y":"-25.0002823","timeToReact":"99","screenV":"99","time":"59.61147"},{"spawnID":"156","spawnType":"Bonus","eventType":"Catch","eventCat":"Positive","x":"9.468772","timeToReact":"4.45311","screenV":"6.57131","time":"59.72344"},{"spawnID":"158","spawnType":"Enemy","eventType":"Kill","eventCat":"Positive","x":"6.509018","timeToReact":"3.5212863","screenV":"4.76094","time":"59.72382"},{"spawnID":"158","spawnType":"Enemy","eventType":"Hit","eventCat":"Positive","x":"6.509018","timeToReact":"3.5213089","screenV":"4.76091","time":"59.7238426"},{"spawnID":"157","spawnType":"Bonus","eventType":"Catch","eventCat":"Positive","x":"2.924495","timeToReact":"4.2349733","screenV":"6.52486","time":"60.0842133"},{"spawnID":"159","spawnType":"Bonus","eventType":"Catch","eventCat":"Positive","x":"4.371002","timeToReact":"4.1701241","screenV":"6.67147","time":"60.58107"},{"spawnID":"150","spawnType":"Obstacle","eventType":"Dodge","eventCat":"Neutral","x":"15.7790146","timeToReact":"99","screenV":"99","time":"60.8003159"},{"spawnID":"151","spawnType":"Obstacle","eventType":"Dodge","eventCat":"Neutral","x":"-7.689231","timeToReact":"99","screenV":"99","time":"60.80033"},{"spawnID":"148","spawnType":"Enemy","eventType":"Miss","eventCat":"Neutral","x":"-13.938","y":"-25.02966","timeToReact":"99","screenV":"99","time":"61.04225"},{"spawnID":"153","spawnType":"Obstacle","eventType":"Dodge","eventCat":"Neutral","x":"15.7271309","timeToReact":"99","screenV":"99","time":"61.1326828"},{"spawnID":"168","spawnType":"Enemy","eventType":"Hit","eventCat":"Positive","x":"6.839102","timeToReact":"2.5986404","screenV":"5.94199","time":"61.6405563"},{"spawnID":"168","spawnType":"Enemy","eventType":"Kill","eventCat":"Positive","x":"6.839102","timeToReact":"2.7462387","screenV":"5.95523","time":"61.7881546"},{"spawnID":"168","spawnType":"Enemy","eventType":"Hit","eventCat":"Positive","x":"6.839102","timeToReact":"2.7463684","screenV":"5.95495","time":"61.7882843"},{"spawnID":"162","spawnType":"Bonus","eventType":"Catch","eventCat":"Positive","x":"11.4422369","timeToReact":"4.2573815","screenV":"6.41933","time":"61.8078156"},{"spawnID":"164","spawnType":"Bonus","eventType":"Catch","eventCat":"Positive","x":"1.849227","timeToReact":"4.6150856","screenV":"6.04965","time":"62.7488632"},{"spawnID":"166","spawnType":"Bonus","eventType":"Catch","eventCat":"Positive","x":"5.47002","timeToReact":"4.6072998","screenV":"6.01476","time":"63.3422623"},{"spawnID":"160","spawnType":"Obstacle","eventType":"Dodge","eventCat":"Neutral","x":"1.36854362","timeToReact":"99","screenV":"99","time":"63.56584"},{"spawnID":"169","spawnType":"Bonus","eventType":"Catch","eventCat":"Positive","x":"10.7713461","timeToReact":"4.4305472","screenV":"6.13892","time":"63.73105"},{"spawnID":"175","spawnType":"Enemy","eventType":"Kill","eventCat":"Positive","x":"3.61068749","timeToReact":"2.2642756","screenV":"6.98257","time":"64.1319656"},{"spawnID":"175","spawnType":"Enemy","eventType":"Hit","eventCat":"Positive","x":"3.61068749","timeToReact":"2.2644053","screenV":"6.98217","time":"64.1320953"},{"spawnID":"161","spawnType":"Bonus","eventType":"Miss","eventCat":"Neutral","x":"-6.80823946","timeToReact":"99","screenV":"99","time":"64.44443"},{"spawnID":"171","spawnType":"Bonus","eventType":"Catch","eventCat":"Positive","x":"-5.38091373","timeToReact":"4.4445743","screenV":"6.08119","time":"64.8683243"},{"spawnID":"173","spawnType":"Bonus","eventType":"Catch","eventCat":"Positive","x":"-4.71076345","timeToReact":"4.0261077","screenV":"6.54581","time":"65.0427856"},{"spawnID":"165","spawnType":"Obstacle","eventType":"Dodge","eventCat":"Neutral","x":"-14.2155113","timeToReact":"99","screenV":"99","time":"65.60391"},{"spawnID":"174","spawnType":"Bonus","eventType":"Catch","eventCat":"Positive","x":"5.29350567","timeToReact":"4.2127367","screenV":"6.45656","time":"65.78958"},{"spawnID":"167","spawnType":"Obstacle","eventType":"Dodge","eventCat":"Neutral","x":"-8.394458","timeToReact":"99","screenV":"99","time":"65.92253"},{"spawnID":"176","spawnType":"Bonus","eventType":"Catch","eventCat":"Positive","x":"8.952502","timeToReact":"4.10177","screenV":"6.30252","time":"66.25706"},{"spawnID":"177","spawnType":"Bonus","eventType":"Catch","eventCat":"Positive","x":"-1.954472","timeToReact":"4.35703","screenV":"6.46228","time":"67.0771"},{"spawnID":"170","spawnType":"Bonus","eventType":"Miss","eventCat":"Neutral","x":"-7.15543652","timeToReact":"99","screenV":"99","time":"67.29042"},{"spawnID":"179","spawnType":"Bonus","eventType":"Catch","eventCat":"Positive","x":"1.73948944","timeToReact":"4.41201","screenV":"6.19228","time":"67.74633"},{"spawnID":"181","spawnType":"Bonus","eventType":"Catch","eventCat":"Positive","x":"-2.184778","timeToReact":"4.15111","screenV":"6.34210","time":"68.06567"},{"spawnID":"182","spawnType":"Bonus","eventType":"Catch","eventCat":"Positive","x":"-5.68867636","timeToReact":"4.0772","screenV":"6.41261","time":"68.5624"},{"spawnID":"185","spawnType":"Bonus","eventType":"Catch","eventCat":"Positive","x":"7.24207973","timeToReact":"4.3502953","screenV":"6.39167","time":"69.40364"},{"spawnID":"186","spawnType":"Bonus","eventType":"Catch","eventCat":"Positive","x":"10.8440161","timeToReact":"4.07549","screenV":"6.80892","time":"69.70753"},{"spawnID":"172","spawnType":"Enemy","eventType":"Miss","eventCat":"Neutral","x":"-14.6256886","y":"-24.8382568","timeToReact":"99","screenV":"99","time":"70.19739"},{"spawnID":"188","spawnType":"Bonus","eventType":"Catch","eventCat":"Positive","x":"1.6038512","timeToReact":"4.1972259","screenV":"6.59126","time":"70.39617"},{"spawnID":"180","spawnType":"Obstacle","eventType":"Dodge","eventCat":"Neutral","x":"11.0615005","timeToReact":"99","screenV":"99","time":"70.69366"},{"spawnID":"178","spawnType":"Enemy","eventType":"Miss","eventCat":"Neutral","x":"-12.8065987","y":"-25.2751522","timeToReact":"99","screenV":"99","time":"71.02667"},{"spawnID":"198","spawnType":"Enemy","eventType":"Kill","eventCat":"Positive","x":"7.762817","timeToReact":"2.1316138","screenV":"7.24501","time":"71.1116638"},{"spawnID":"198","spawnType":"Enemy","eventType":"Hit","eventCat":"Positive","x":"7.762817","timeToReact":"2.1317054","screenV":"7.24470","time":"71.1117554"},{"spawnID":"183","spawnType":"Obstacle","eventType":"Dodge","eventCat":"Neutral","x":"-11.0214386","timeToReact":"99","screenV":"99","time":"71.41823"},{"spawnID":"190","spawnType":"Bonus","eventType":"Catch","eventCat":"Positive","x":"6.131425","timeToReact":"4.15377","screenV":"6.67750","time":"71.48309"},{"spawnID":"192","spawnType":"Bonus","eventType":"Catch","eventCat":"Positive","x":"-2.31832719","timeToReact":"4.36286","screenV":"6.75199","time":"72.2729"},{"spawnID":"194","spawnType":"Bonus","eventType":"Catch","eventCat":"Positive","x":"-0.6139953","timeToReact":"4.3778947","screenV":"6.19963","time":"72.8394547"},{"spawnID":"193","spawnType":"Obstacle","eventType":"Collision","eventCat":"Negative","x":"3.52898979","timeToReact":"4.8757939","screenV":"5.96572","time":"73.0681839"},{"spawnID":"187","spawnType":"Enemy","eventType":"Miss","eventCat":"Neutral","x":"13.4474068","y":"-25.0258732","timeToReact":"99","screenV":"99","time":"73.77089"},{"spawnID":"201","spawnType":"Bonus","eventType":"Catch","eventCat":"Positive","x":"3.85115957","timeToReact":"4.2364841","screenV":"6.62630","time":"73.8562241"},{"spawnID":"189","spawnType":"Bonus","eventType":"Miss","eventCat":"Neutral","x":"13.6105108","timeToReact":"99","screenV":"99","time":"74.02124"},{"spawnID":"184","spawnType":"Enemy","eventType":"Miss","eventCat":"Neutral","x":"9.364687","y":"-24.83533","timeToReact":"99","screenV":"99","time":"74.28942"},{"spawnID":"199","spawnType":"Bonus","eventType":"Catch","eventCat":"Positive","x":"-2.921621","timeToReact":"5.672536","screenV":"5.35004","time":"74.723526"},{"spawnID":"193","spawnType":"Obstacle","eventType":"Dodge","eventCat":"Neutral","x":"3.52898979","timeToReact":"99","screenV":"99","time":"75.04129"},{"spawnID":"191","spawnType":"Enemy","eventType":"Miss","eventCat":"Neutral","x":"15.3378868","y":"-25.112236","timeToReact":"99","screenV":"99","time":"75.21066"},{"spawnID":"195","spawnType":"Obstacle","eventType":"Dodge","eventCat":"Neutral","x":"-4.390033","timeToReact":"99","screenV":"99","time":"75.57757"},{"spawnID":"196","spawnType":"Obstacle","eventType":"Dodge","eventCat":"Neutral","x":"14.4442368","timeToReact":"99","screenV":"99","time":"75.7447052"},{"spawnID":"197","spawnType":"Obstacle","eventType":"Dodge","eventCat":"Neutral","x":"-2.60358238","timeToReact":"99","screenV":"99","time":"75.81207"},{"spawnID":"200","spawnType":"Obstacle","eventType":"Dodge","eventCat":"Neutral","x":"-8.048129","timeToReact":"99","screenV":"99","time":"76.38186"},{"spawnID":"202","spawnType":"Bonus","eventType":"Catch","eventCat":"Positive","x":"3.74134326","timeToReact":"3.40399","screenV":"7.81399","time":"83.86327"},{"spawnID":"203","spawnType":"Bonus","eventType":"Catch","eventCat":"Positive","x":"-3.62856841","timeToReact":"3.633255","screenV":"7.34671","time":"84.52565"},{"spawnID":"205","spawnType":"Bonus","eventType":"Catch","eventCat":"Positive","x":"3.121027","timeToReact":"3.82161","screenV":"7.19076","time":"85.15025"},{"spawnID":"208","spawnType":"Bonus","eventType":"Catch","eventCat":"Positive","x":"-8.256483","timeToReact":"4.10374","screenV":"6.93397","time":"86.30007"},{"spawnID":"206","spawnType":"Bonus","eventType":"Catch","eventCat":"Positive","x":"-11.4122248","timeToReact":"4.76957","screenV":"5.77713","time":"86.53017"},{"spawnID":"209","spawnType":"Bonus","eventType":"Catch","eventCat":"Positive","x":"-9.845229","timeToReact":"4.1644648","screenV":"6.39426","time":"86.8096848"},{"spawnID":"204","spawnType":"Enemy","eventType":"Miss","eventCat":"Neutral","x":"-11.4460373","y":"-24.9792233","timeToReact":"99","screenV":"99","time":"86.99176"},{"spawnID":"211","spawnType":"Bonus","eventType":"Catch","eventCat":"Positive","x":"3.07925224","timeToReact":"4.61259","screenV":"6.13542","time":"87.76472"},{"spawnID":"214","spawnType":"Bonus","eventType":"Catch","eventCat":"Positive","x":"9.07146549","timeToReact":"4.40124","screenV":"6.30079","time":"88.08513"},{"spawnID":"218","spawnType":"Bonus","eventType":"Catch","eventCat":"Positive","x":"9.063566","timeToReact":"4.4771805","screenV":"6.15739","time":"88.7356949"},{"spawnID":"220","spawnType":"Obstacle","eventType":"Collision","eventCat":"Negative","x":"6.2899","timeToReact":"4.82966","screenV":"5.89687","time":"89.52257"},{"spawnID":"210","spawnType":"Obstacle","eventType":"Dodge","eventCat":"Neutral","x":"-15.8369293","timeToReact":"99","screenV":"99","time":"89.66912"},{"spawnID":"223","spawnType":"Bonus","eventType":"Catch","eventCat":"Positive","x":"3.19968724","timeToReact":"4.9840252","screenV":"5.87070","time":"89.7970352"},{"spawnID":"226","spawnType":"Enemy","eventType":"Kill","eventCat":"Positive","x":"1.69322777","timeToReact":"3.93451","screenV":"5.89108","time":"90.12241"},{"spawnID":"226","spawnType":"Enemy","eventType":"Hit","eventCat":"Positive","x":"1.69322777","timeToReact":"3.93453","screenV":"5.89105","time":"90.12243"},{"spawnID":"225","spawnType":"Bonus","eventType":"Catch","eventCat":"Positive","x":"-2.74184847","timeToReact":"4.274995","screenV":"6.59465","time":"90.223465"},{"spawnID":"224","spawnType":"Bonus","eventType":"Catch","eventCat":"Positive","x":"-5.942276","timeToReact":"4.95713","screenV":"5.76239","time":"90.33824"},{"spawnID":"213","spawnType":"Obstacle","eventType":"Dodge","eventCat":"Neutral","x":"-2.19246864","timeToReact":"99","screenV":"99","time":"90.56943"},{"spawnID":"215","spawnType":"Obstacle","eventType":"Dodge","eventCat":"Neutral","x":"5.88651848","timeToReact":"99","screenV":"99","time":"90.81956"},{"spawnID":"216","spawnType":"Obstacle","eventType":"Dodge","eventCat":"Neutral","x":"-10.3454514","timeToReact":"99","screenV":"99","time":"90.8510056"},{"spawnID":"217","spawnType":"Obstacle","eventType":"Dodge","eventCat":"Neutral","x":"-3.3392086","timeToReact":"99","screenV":"99","time":"90.8817139"},{"spawnID":"227","spawnType":"Bonus","eventType":"Catch","eventCat":"Positive","x":"-9.916194","timeToReact":"4.377225","screenV":"6.13858","time":"90.915535"},{"spawnID":"228","spawnType":"Bonus","eventType":"Catch","eventCat":"Positive","x":"-2.059383","timeToReact":"4.34898","screenV":"6.37090","time":"91.48487"},{"spawnID":"219","spawnType":"Obstacle","eventType":"Dodge","eventCat":"Neutral","x":"-13.0672913","timeToReact":"99","screenV":"99","time":"91.4944153"},{"spawnID":"220","spawnType":"Obstacle","eventType":"Dodge","eventCat":"Neutral","x":"6.2899","timeToReact":"99","screenV":"99","time":"91.5492249"},{"spawnID":"221","spawnType":"Obstacle","eventType":"Dodge","eventCat":"Neutral","x":"-6.678252","timeToReact":"99","screenV":"99","time":"91.60032"},{"spawnID":"236","spawnType":"Enemy","eventType":"Kill","eventCat":"Positive","x":"-0.361603916","timeToReact":"2.959805","screenV":"7.10547","time":"92.010025"},{"spawnID":"236","spawnType":"Enemy","eventType":"Hit","eventCat":"Positive","x":"-0.361603916","timeToReact":"2.9598355","screenV":"7.10540","time":"92.0100555"},{"spawnID":"231","spawnType":"Bonus","eventType":"Catch","eventCat":"Positive","x":"3.484191","timeToReact":"4.38810","screenV":"6.46890","time":"92.09387"},{"spawnID":"232","spawnType":"Bonus","eventType":"Catch","eventCat":"Positive","x":"7.661852","timeToReact":"4.38143","screenV":"6.67040","time":"92.63927"},{"spawnID":"248","spawnType":"Bonus","eventType":"Miss","eventCat":"Neutral","x":"0.686496258","timeToReact":"99","screenV":"99","time":"93.4685745"},{"spawnID":"237","spawnType":"Bonus","eventType":"Catch","eventCat":"Positive","x":"10.2167158","timeToReact":"4.07440","screenV":"6.66244","time":"93.46861"},{"spawnID":"254","spawnType":"Bonus","eventType":"Miss","eventCat":"Neutral","x":"1.58646834","timeToReact":"99","screenV":"99","time":"93.7065048"},{"spawnID":"253","spawnType":"Bonus","eventType":"Miss","eventCat":"Neutral","x":"0.6827049","timeToReact":"99","screenV":"99","time":"93.7368"},{"spawnID":"251","spawnType":"Bonus","eventType":"Miss","eventCat":"Neutral","x":"1.76063561","timeToReact":"99","screenV":"99","time":"93.77282"},{"spawnID":"258","spawnType":"Bonus","eventType":"Miss","eventCat":"Neutral","x":"1.56692541","timeToReact":"99","screenV":"99","time":"93.7728348"},{"spawnID":"252","spawnType":"Bonus","eventType":"Miss","eventCat":"Neutral","x":"1.62098837","timeToReact":"99","screenV":"99","time":"93.80448"},{"spawnID":"257","spawnType":"Bonus","eventType":"Miss","eventCat":"Neutral","x":"1.683434","timeToReact":"99","screenV":"99","time":"93.80451"},{"spawnID":"256","spawnType":"Bonus","eventType":"Miss","eventCat":"Neutral","x":"1.89573872","timeToReact":"99","screenV":"99","time":"93.84014"},{"spawnID":"255","spawnType":"Bonus","eventType":"Miss","eventCat":"Neutral","x":"2.21165562","timeToReact":"99","screenV":"99","time":"93.87056"},{"spawnID":"250","spawnType":"Bonus","eventType":"Miss","eventCat":"Neutral","x":"1.15643227","timeToReact":"99","screenV":"99","time":"93.870575"},{"spawnID":"235","spawnType":"Bonus","eventType":"Catch","eventCat":"Positive","x":"1.2239641","timeToReact":"5.17558","screenV":"5.51096","time":"94.0046"},{"spawnID":"249","spawnType":"Bonus","eventType":"Miss","eventCat":"Neutral","x":"1.35674536","timeToReact":"99","screenV":"99","time":"94.03769"},{"spawnID":"229","spawnType":"Obstacle","eventType":"Dodge","eventCat":"Neutral","x":"8.856693","timeToReact":"99","screenV":"99","time":"94.05367"},{"spawnID":"239","spawnType":"Obstacle","eventType":"Collision","eventCat":"Negative","x":"-7.691184","timeToReact":"4.3426051","screenV":"5.96365","time":"94.34761"},{"spawnID":"238","spawnType":"Bonus","eventType":"Catch","eventCat":"Positive","x":"-8.81896","timeToReact":"4.5722355","screenV":"6.18466","time":"94.5423355"},{"spawnID":"240","spawnType":"Enemy","eventType":"Hit","eventCat":"Positive","x":"-8.857795","timeToReact":"4.3910459","screenV":"5.96335","time":"94.8424759"},{"spawnID":"240","spawnType":"Enemy","eventType":"Collision","eventCat":"Negative","x":"-8.857795","y":"-6.421652","timeToReact":"4.52746","screenV":"5.95725","time":"94.97889"},{"spawnID":"239","spawnType":"Obstacle","eventType":"Collision","eventCat":"Negative","x":"-7.691184","timeToReact":"5.0363312","screenV":"5.96542","time":"95.0413361"},{"spawnID":"233","spawnType":"Obstacle","eventType":"Dodge","eventCat":"Neutral","x":"-13.4037552","timeToReact":"99","screenV":"99","time":"95.12077"},{"spawnID":"242","spawnType":"Bonus","eventType":"Catch","eventCat":"Positive","x":"-7.359186","timeToReact":"4.08095","screenV":"6.76213","time":"95.20192"},{"spawnID":"234","spawnType":"Obstacle","eventType":"Dodge","eventCat":"Neutral","x":"3.801817","timeToReact":"99","screenV":"99","time":"95.28138"},{"spawnID":"245","spawnType":"Enemy","eventType":"Hit","eventCat":"Positive","x":"-5.59680462","timeToReact":"3.75020","screenV":"5.93424","time":"95.59768"},{"spawnID":"243","spawnType":"Bonus","eventType":"Catch","eventCat":"Positive","x":"8.478589","timeToReact":"4.31429","screenV":"6.53117","time":"96.0003"},{"spawnID":"244","spawnType":"Obstacle","eventType":"Collision","eventCat":"Negative","x":"13.9599762","timeToReact":"4.4682547","screenV":"5.93994","time":"96.23729"},{"spawnID":"241","spawnType":"Bonus","eventType":"Catch","eventCat":"Positive","x":"10.7724648","timeToReact":"5.78793","screenV":"5.19407","time":"96.32233"},{"spawnID":"230","spawnType":"Enemy","eventType":"Miss","eventCat":"Neutral","x":"-12.6250944","y":"-24.8919811","timeToReact":"99","screenV":"99","time":"96.54832"},{"spawnID":"239","spawnType":"Obstacle","eventType":"Dodge","eventCat":"Neutral","x":"-7.691184","timeToReact":"99","screenV":"99","time":"96.84959"},{"spawnID":"246","spawnType":"Bonus","eventType":"Catch","eventCat":"Positive","x":"-1.11672211","timeToReact":"4.7433744","screenV":"5.99746","time":"96.9856644"},{"spawnID":"259","spawnType":"Enemy","eventType":"Kill","eventCat":"Positive","x":"9.511042","timeToReact":"3.83448","screenV":"4.67844","time":"97.08404"},{"spawnID":"259","spawnType":"Enemy","eventType":"Hit","eventCat":"Positive","x":"9.511042","timeToReact":"3.83451","screenV":"4.67840","time":"97.08407"},{"spawnID":"247","spawnType":"Bonus","eventType":"Catch","eventCat":"Positive","x":"5.90342426","timeToReact":"4.80531","screenV":"5.90695","time":"97.60821"},{"spawnID":"261","spawnType":"Bonus","eventType":"Catch","eventCat":"Positive","x":"-4.096716","timeToReact":"5.0148941","screenV":"5.71837","time":"98.39039"},{"spawnID":"265","spawnType":"Enemy","eventType":"Kill","eventCat":"Positive","x":"3.51015425","timeToReact":"3.7760962","screenV":"4.62971","time":"98.4564362"},{"spawnID":"265","spawnType":"Enemy","eventType":"Hit","eventCat":"Positive","x":"3.51015425","timeToReact":"3.77613","screenV":"4.62967","time":"98.45647"},{"spawnID":"262","spawnType":"Bonus","eventType":"Catch","eventCat":"Positive","x":"-7.00820351","timeToReact":"4.57070","screenV":"6.09083","time":"98.52365"},{"spawnID":"244","spawnType":"Obstacle","eventType":"Dodge","eventCat":"Neutral","x":"13.9599762","timeToReact":"99","screenV":"99","time":"98.6561"},{"spawnID":"269","spawnType":"Enemy","eventType":"Kill","eventCat":"Positive","x":"-4.414048","timeToReact":"3.2598347","screenV":"4.62716","time":"99.3440247"},{"spawnID":"269","spawnType":"Enemy","eventType":"Hit","eventCat":"Positive","x":"-4.414048","timeToReact":"3.26010","screenV":"4.62679","time":"99.34429"},{"spawnID":"263","spawnType":"Bonus","eventType":"Catch","eventCat":"Positive","x":"-0.0955385","timeToReact":"4.90011","screenV":"5.89642","time":"99.4283"},{"spawnID":"245","spawnType":"Enemy","eventType":"Miss","eventCat":"Neutral","x":"-5.59680462","y":"-25.0166473","timeToReact":"99","screenV":"99","time":"99.54565"},{"spawnID":"267","spawnType":"Bonus","eventType":"Catch","eventCat":"Positive","x":"2.04606152","timeToReact":"4.583504","screenV":"6.12058","time":"99.659874"},{"spawnID":"268","spawnType":"Bonus","eventType":"Catch","eventCat":"Positive","x":"6.60490656","timeToReact":"4.426047","screenV":"6.15495","time":"100.095467"},{"spawnID":"260","spawnType":"Obstacle","eventType":"Dodge","eventCat":"Neutral","x":"15.879612","timeToReact":"99","screenV":"99","time":"100.1491"},{"spawnID":"270","spawnType":"Bonus","eventType":"Catch","eventCat":"Positive","x":"9.778596","timeToReact":"4.571591","screenV":"6.44282","time":"100.817451"},{"spawnID":"274","spawnType":"Enemy","eventType":"Hit","eventCat":"Positive","x":"11.0848808","timeToReact":"3.487674","screenV":"5.92550","time":"100.999634"},{"spawnID":"274","spawnType":"Enemy","eventType":"Kill","eventCat":"Positive","x":"11.0848808","timeToReact":"3.657367","screenV":"5.92536","time":"101.169327"},{"spawnID":"274","spawnType":"Enemy","eventType":"Hit","eventCat":"Positive","x":"11.0848808","timeToReact":"3.657489","screenV":"5.92516","time":"101.169449"},{"spawnID":"264","spawnType":"Obstacle","eventType":"Dodge","eventCat":"Neutral","x":"4.54697227","timeToReact":"99","screenV":"99","time":"101.568977"},{"spawnID":"273","spawnType":"Bonus","eventType":"Catch","eventCat":"Positive","x":"4.459011","timeToReact":"4.294839","screenV":"6.56265","time":"101.673019"},{"spawnID":"266","spawnType":"Obstacle","eventType":"Dodge","eventCat":"Neutral","x":"-11.5711861","timeToReact":"99","screenV":"99","time":"101.80439"},{"spawnID":"272","spawnType":"Bonus","eventType":"Catch","eventCat":"Positive","x":"-0.7374012","timeToReact":"5.0323261","screenV":"5.97669","time":"101.840012"},{"spawnID":"276","spawnType":"Obstacle","eventType":"Collision","eventCat":"Negative","x":"-2.546049","timeToReact":"4.3079044","screenV":"5.88092","time":"102.1228"},{"spawnID":"279","spawnType":"Enemy","eventType":"Kill","eventCat":"Positive","x":"7.713248","timeToReact":"3.293286","screenV":"4.60601","time":"102.238686"},{"spawnID":"279","spawnType":"Enemy","eventType":"Hit","eventCat":"Positive","x":"7.713248","timeToReact":"3.293316","screenV":"4.60597","time":"102.238716"},{"spawnID":"277","spawnType":"Bonus","eventType":"Catch","eventCat":"Positive","x":"0.278064072","timeToReact":"4.27663","screenV":"6.29142","time":"102.2563"},{"spawnID":"278","spawnType":"Bonus","eventType":"Catch","eventCat":"Positive","x":"1.23779559","timeToReact":"4.48725","screenV":"6.65588","time":"103.06031"},{"spawnID":"281","spawnType":"Bonus","eventType":"Catch","eventCat":"Positive","x":"-4.79332924","timeToReact":"4.242683","screenV":"6.35058","time":"103.380463"},{"spawnID":"271","spawnType":"Obstacle","eventType":"Dodge","eventCat":"Neutral","x":"-1.34763527","timeToReact":"99","screenV":"99","time":"103.393379"},{"spawnID":"280","spawnType":"Obstacle","eventType":"Collision","eventCat":"Negative","x":"0.377271652","timeToReact":"4.877662","screenV":"5.88488","time":"104.013962"},{"spawnID":"282","spawnType":"Bonus","eventType":"Catch","eventCat":"Positive","x":"4.40810347","timeToReact":"4.6490476","screenV":"6.06345","time":"104.350662"},{"spawnID":"275","spawnType":"Obstacle","eventType":"Dodge","eventCat":"Neutral","x":"-6.09820461","timeToReact":"99","screenV":"99","time":"104.504807"},{"spawnID":"283","spawnType":"Bonus","eventType":"Catch","eventCat":"Positive","x":"6.884193","timeToReact":"4.285232","screenV":"6.63161","time":"104.565582"},{"spawnID":"276","spawnType":"Obstacle","eventType":"Dodge","eventCat":"Neutral","x":"-2.546049","timeToReact":"99","screenV":"99","time":"104.699211"},{"spawnID":"285","spawnType":"Bonus","eventType":"Catch","eventCat":"Positive","x":"3.42754531","timeToReact":"4.391411","screenV":"6.54771","time":"105.236244"},{"spawnID":"287","spawnType":"Enemy","eventType":"Kill","eventCat":"Positive","x":"1.27940536","timeToReact":"3.470329","screenV":"4.65358","time":"105.267975"},{"spawnID":"287","spawnType":"Enemy","eventType":"Hit","eventCat":"Positive","x":"1.27940536","timeToReact":"3.470359","screenV":"4.65354","time":"105.268005"},{"spawnID":"286","spawnType":"Bonus","eventType":"Catch","eventCat":"Positive","x":"-1.79165018","timeToReact":"4.289216","screenV":"6.74885","time":"105.707993"},{"spawnID":"280","spawnType":"Obstacle","eventType":"Dodge","eventCat":"Neutral","x":"0.377271652","timeToReact":"99","screenV":"99","time":"106.003555"},{"spawnID":"284","spawnType":"Enemy","eventType":"Hurt","eventCat":"Negative","x":"-4.93127632","timeToReact":"5.720062","screenV":"4.97429","time":"106.105629"},{"spawnID":"288","spawnType":"Bonus","eventType":"Catch","eventCat":"Positive","x":"-7.160768","timeToReact":"4.276411","screenV":"6.33454","time":"106.289711"},{"spawnID":"289","spawnType":"Bonus","eventType":"Catch","eventCat":"Positive","x":"4.0914855","timeToReact":"4.364082","screenV":"6.07226","time":"106.962326"},{"spawnID":"295","spawnType":"Enemy","eventType":"Hit","eventCat":"Positive","x":"-6.334571","timeToReact":"2.787529","screenV":"5.81720","time":"107.406258"},{"spawnID":"290","spawnType":"Bonus","eventType":"Catch","eventCat":"Positive","x":"-8.091282","timeToReact":"4.721687","screenV":"6.00755","time":"107.888763"},{"spawnID":"284","spawnType":"Enemy","eventType":"Miss","eventCat":"Neutral","x":"-13.7612343","y":"-25.0634785","timeToReact":"99","screenV":"99","time":"108.170464"},{"spawnID":"293","spawnType":"Bonus","eventType":"Catch","eventCat":"Positive","x":"-10.3668032","timeToReact":"4.449965","screenV":"6.15686","time":"108.1705"},{"spawnID":"295","spawnType":"Enemy","eventType":"Kill","eventCat":"Positive","x":"-6.334571","timeToReact":"3.778171","screenV":"5.78316","time":"108.3969"},{"spawnID":"295","spawnType":"Enemy","eventType":"Hit","eventCat":"Positive","x":"-6.334571","timeToReact":"3.778206","screenV":"5.78311","time":"108.396935"},{"spawnID":"294","spawnType":"Bonus","eventType":"Catch","eventCat":"Positive","x":"-8.089383","timeToReact":"4.326805","screenV":"6.17745","time":"108.608459"},{"spawnID":"296","spawnType":"Bonus","eventType":"Catch","eventCat":"Positive","x":"-1.40274358","timeToReact":"4.331085","screenV":"6.51940","time":"109.183769"},{"spawnID":"297","spawnType":"Bonus","eventType":"Catch","eventCat":"Positive","x":"1.87398589","timeToReact":"4.073646","screenV":"6.28459","time":"109.525772"},{"spawnID":"299","spawnType":"Bonus","eventType":"Catch","eventCat":"Positive","x":"3.939396","timeToReact":"4.348099","screenV":"6.19204","time":"110.353226"},{"spawnID":"292","spawnType":"Obstacle","eventType":"Dodge","eventCat":"Neutral","x":"-4.61625957","timeToReact":"99","screenV":"99","time":"110.521591"},{"spawnID":"301","spawnType":"Bonus","eventType":"Catch","eventCat":"Positive","x":"0.759500563","timeToReact":"4.452209","screenV":"6.40217","time":"111.026161"},{"spawnID":"304","spawnType":"Enemy","eventType":"Kill","eventCat":"Positive","x":"-1.97166717","timeToReact":"4.237754","screenV":"4.70455","time":"111.744781"},{"spawnID":"304","spawnType":"Enemy","eventType":"Hit","eventCat":"Positive","x":"-1.97166717","timeToReact":"4.237907","screenV":"4.70438","time":"111.744934"},{"spawnID":"300","spawnType":"Enemy","eventType":"Collision","eventCat":"Negative","x":"5.919799","y":"-6.830332","timeToReact":"5.979515","screenV":"4.57895","time":"112.008583"},{"spawnID":"305","spawnType":"Bonus","eventType":"Catch","eventCat":"Positive","x":"6.89506435","timeToReact":"4.361465","screenV":"6.32549","time":"112.162445"},{"spawnID":"303","spawnType":"Bonus","eventType":"Catch","eventCat":"Positive","x":"8.553401","timeToReact":"5.044732","screenV":"5.65026","time":"112.248917"},{"spawnID":"298","spawnType":"Obstacle","eventType":"Dodge","eventCat":"Neutral","x":"8.148899","timeToReact":"99","screenV":"99","time":"112.447914"},{"spawnID":"291","spawnType":"Enemy","eventType":"Miss","eventCat":"Neutral","x":"15.496357","y":"-24.8215637","timeToReact":"99","screenV":"99","time":"112.985664"},{"spawnID":"308","spawnType":"Bonus","eventType":"Catch","eventCat":"Positive","x":"3.101286","timeToReact":"4.317894","screenV":"6.55659","time":"113.253853"},{"spawnID":"306","spawnType":"Bonus","eventType":"Catch","eventCat":"Positive","x":"-2.10565877","timeToReact":"5.151239","screenV":"5.74444","time":"113.5226"},{"spawnID":"302","spawnType":"Obstacle","eventType":"Dodge","eventCat":"Neutral","x":"8.39038849","timeToReact":"99","screenV":"99","time":"113.719261"},{"spawnID":"309","spawnType":"Bonus","eventType":"Catch","eventCat":"Positive","x":"4.064542","timeToReact":"4.644638","screenV":"6.11485","time":"114.138367"},{"spawnID":"307","spawnType":"Enemy","eventType":"Miss","eventCat":"Neutral","x":"-15.3038254","y":"-25.2231483","timeToReact":"99","screenV":"99","time":"116.329109"}]}