{"sessionID":"557ef3cc151b0fd017758131","patientId":"557eef07151b0fd017758129","date":"2015-06-15 17:48:28","exerciseType":"HANDPOINT","exerciseDirection":"HORIZONTAL","nbRepetitions":"3","actionPhaseDuration":"30","restPhaseDuration":"10","score":"620","performance":"0.12375365171945016","completed":"true","duration":"120.0122","logs":[{"spawnID":"3","spawnType":"Obstacle","eventType":"Collision","eventCat":"Negative","x":"1.46337318","timeToReact":"4.23575187","screenV":"5.96790","time":"5.8965106"},{"spawnID":"6","spawnType":"Bonus","eventType":"Catch","eventCat":"Positive","x":"-0.984630346","timeToReact":"4.4034537","screenV":"6.23088","time":"6.9502387"},{"spawnID":"9","spawnType":"Enemy","eventType":"Hit","eventCat":"Positive","x":"4.46264458","timeToReact":"2.86405172","screenV":"5.93174","time":"7.069137"},{"spawnID":"9","spawnType":"Enemy","eventType":"Kill","eventCat":"Positive","x":"4.46264458","timeToReact":"3.67007637","screenV":"5.96570","time":"7.87516165"},{"spawnID":"9","spawnType":"Enemy","eventType":"Hit","eventCat":"Positive","x":"4.46264458","timeToReact":"3.67043672","screenV":"5.96511","time":"7.875522"},{"spawnID":"1","spawnType":"Obstacle","eventType":"Dodge","eventCat":"Neutral","x":"-7.15681744","timeToReact":"99","screenV":"99","time":"7.970058"},{"spawnID":"3","spawnType":"Obstacle","eventType":"Dodge","eventCat":"Neutral","x":"1.46337318","timeToReact":"99","screenV":"99","time":"8.490242"},{"spawnID":"2","spawnType":"Bonus","eventType":"Miss","eventCat":"Neutral","x":"15.0206461","timeToReact":"99","screenV":"99","time":"8.877096"},{"spawnID":"4","spawnType":"Bonus","eventType":"Miss","eventCat":"Neutral","x":"8.658386","timeToReact":"99","screenV":"99","time":"9.226095"},{"spawnID":"12","spawnType":"Bonus","eventType":"Catch","eventCat":"Positive","x":"5.072734","timeToReact":"4.56999231","screenV":"6.17707","time":"9.947891"},{"spawnID":"16","spawnType":"Bonus","eventType":"Catch","eventCat":"Positive","x":"9.718578","timeToReact":"4.11847166","screenV":"6.41650","time":"10.6336079"},{"spawnID":"7","spawnType":"Bonus","eventType":"Miss","eventCat":"Neutral","x":"-12.2142448","timeToReact":"99","screenV":"99","time":"10.664854"},{"spawnID":"8","spawnType":"Bonus","eventType":"Miss","eventCat":"Neutral","x":"-8.368568","timeToReact":"99","screenV":"99","time":"11.2392044"},{"spawnID":"17","spawnType":"Bonus","eventType":"Catch","eventCat":"Positive","x":"5.152538","timeToReact":"4.4689239","screenV":"6.31197","time":"11.5849419"},{"spawnID":"10","spawnType":"Bonus","eventType":"Miss","eventCat":"Neutral","x":"-7.309124","timeToReact":"99","screenV":"99","time":"11.738781"},{"spawnID":"5","spawnType":"Enemy","eventType":"Miss","eventCat":"Neutral","x":"14.3716965","y":"-24.8821239","timeToReact":"99","screenV":"99","time":"12.1551285"},{"spawnID":"23","spawnType":"Enemy","eventType":"Kill","eventCat":"Positive","x":"6.415641","timeToReact":"3.025318","screenV":"4.73251","time":"12.27166"},{"spawnID":"23","spawnType":"Enemy","eventType":"Hit","eventCat":"Positive","x":"6.415641","timeToReact":"3.0255696","screenV":"4.73212","time":"12.2719116"},{"spawnID":"11","spawnType":"Bonus","eventType":"Miss","eventCat":"Neutral","x":"-4.593837","timeToReact":"99","screenV":"99","time":"12.3220253"},{"spawnID":"13","spawnType":"Obstacle","eventType":"Dodge","eventCat":"Neutral","x":"-10.5810356","timeToReact":"99","screenV":"99","time":"12.4273834"},{"spawnID":"21","spawnType":"Bonus","eventType":"Catch","eventCat":"Positive","x":"5.239365","timeToReact":"4.3053496","screenV":"6.29119","time":"12.5439186"},{"spawnID":"15","spawnType":"Bonus","eventType":"Miss","eventCat":"Neutral","x":"-11.496768","timeToReact":"99","screenV":"99","time":"13.7271"},{"spawnID":"19","spawnType":"Obstacle","eventType":"Dodge","eventCat":"Neutral","x":"12.77993","timeToReact":"99","screenV":"99","time":"14.4295006"},{"spawnID":"20","spawnType":"Bonus","eventType":"Miss","eventCat":"Neutral","x":"9.990082","timeToReact":"99","screenV":"99","time":"15.1705894"},{"spawnID":"29","spawnType":"Bonus","eventType":"Catch","eventCat":"Positive","x":"11.9205923","timeToReact":"4.1245079","screenV":"6.67428","time":"15.201046"},{"spawnID":"14","spawnType":"Enemy","eventType":"Miss","eventCat":"Neutral","x":"-5.38698244","y":"-24.8692722","timeToReact":"99","screenV":"99","time":"15.4840393"},{"spawnID":"30","spawnType":"Bonus","eventType":"Catch","eventCat":"Positive","x":"11.0899725","timeToReact":"4.1461830","screenV":"6.39898","time":"15.7853584"},{"spawnID":"31","spawnType":"Bonus","eventType":"Catch","eventCat":"Positive","x":"12.0621","timeToReact":"4.0507965","screenV":"6.39112","time":"16.256134"},{"spawnID":"22","spawnType":"Bonus","eventType":"Miss","eventCat":"Neutral","x":"-7.941392","timeToReact":"99","screenV":"99","time":"16.30532"},{"spawnID":"28","spawnType":"Enemy","eventType":"Hurt","eventCat":"Negative","x":"11.5362244","timeToReact":"5.5265655","screenV":"5.14845","time":"16.4573364"},{"spawnID":"28","spawnType":"Enemy","eventType":"Hurt","eventCat":"Negative","x":"11.6782436","timeToReact":"5.5931053","screenV":"5.08720","time":"16.5238762"},{"spawnID":"28","spawnType":"Enemy","eventType":"Hurt","eventCat":"Negative","x":"11.9270258","timeToReact":"5.6917152","screenV":"4.99906","time":"16.6224861"},{"spawnID":"28","spawnType":"Enemy","eventType":"Hurt","eventCat":"Negative","x":"12.1604586","timeToReact":"5.7754326","screenV":"4.92660","time":"16.7062035"},{"spawnID":"28","spawnType":"Enemy","eventType":"Hurt","eventCat":"Negative","x":"12.5035286","timeToReact":"5.8933563","screenV":"4.82802","time":"16.8241272"},{"spawnID":"24","spawnType":"Bonus","eventType":"Miss","eventCat":"Neutral","x":"-1.330775","timeToReact":"99","screenV":"99","time":"16.8801651"},{"spawnID":"28","spawnType":"Enemy","eventType":"Hurt","eventCat":"Negative","x":"12.8259945","timeToReact":"5.9818535","screenV":"4.75659","time":"16.9126244"},{"spawnID":"28","spawnType":"Enemy","eventType":"Hurt","eventCat":"Negative","x":"13.1764765","timeToReact":"6.0961691","screenV":"4.66740","time":"17.02694"},{"spawnID":"28","spawnType":"Enemy","eventType":"Hurt","eventCat":"Negative","x":"13.2872429","timeToReact":"6.1150245","screenV":"4.65301","time":"17.0457954"},{"spawnID":"28","spawnType":"Enemy","eventType":"Hurt","eventCat":"Negative","x":"13.3967686","timeToReact":"6.1437454","screenV":"4.63125","time":"17.0745163"},{"spawnID":"28","spawnType":"Enemy","eventType":"Collision","eventCat":"Negative","x":"15.5787592","y":"-8.346157","timeToReact":"6.1621666","screenV":"4.68921","time":"17.0929375"},{"spawnID":"28","spawnType":"Enemy","eventType":"Hurt","eventCat":"Negative","x":"13.5546885","timeToReact":"6.1941147","screenV":"4.59359","time":"17.1248856"},{"spawnID":"28","spawnType":"Enemy","eventType":"Hurt","eventCat":"Negative","x":"13.60736","timeToReact":"6.2145080","screenV":"4.57852","time":"17.1452789"},{"spawnID":"18","spawnType":"Enemy","eventType":"Miss","eventCat":"Neutral","x":"-14.1089821","y":"-24.899641","timeToReact":"99","screenV":"99","time":"17.1916542"},{"spawnID":"26","spawnType":"Obstacle","eventType":"Dodge","eventCat":"Neutral","x":"2.39092064","timeToReact":"99","screenV":"99","time":"17.2092514"},{"spawnID":"28","spawnType":"Enemy","eventType":"Hurt","eventCat":"Negative","x":"13.8068552","timeToReact":"6.2792320","screenV":"4.53132","time":"17.2100029"},{"spawnID":"28","spawnType":"Enemy","eventType":"Hurt","eventCat":"Negative","x":"13.9902411","timeToReact":"6.3479728","screenV":"4.48226","time":"17.2787437"},{"spawnID":"28","spawnType":"Enemy","eventType":"Hurt","eventCat":"Negative","x":"14.0775728","timeToReact":"6.3788452","screenV":"4.46056","time":"17.3096161"},{"spawnID":"25","spawnType":"Bonus","eventType":"Miss","eventCat":"Neutral","x":"-5.920728","timeToReact":"99","screenV":"99","time":"17.41275"},{"spawnID":"36","spawnType":"Enemy","eventType":"Kill","eventCat":"Positive","x":"8.349651","timeToReact":"3.3410339","screenV":"4.75056","time":"17.6130447"},{"spawnID":"36","spawnType":"Enemy","eventType":"Hit","eventCat":"Positive","x":"8.349651","timeToReact":"3.3410692","screenV":"4.75051","time":"17.61308"},{"spawnID":"27","spawnType":"Bonus","eventType":"Miss","eventCat":"Neutral","x":"-3.50714684","timeToReact":"99","screenV":"99","time":"18.2614975"},{"spawnID":"41","spawnType":"Bonus","eventType":"Catch","eventCat":"Positive","x":"9.274044","timeToReact":"4.0307125","screenV":"6.38019","time":"19.66898"},{"spawnID":"32","spawnType":"Enemy","eventType":"Miss","eventCat":"Neutral","x":"3.65055275","y":"-25.1383133","timeToReact":"99","screenV":"99","time":"20.2377281"},{"spawnID":"33","spawnType":"Bonus","eventType":"Miss","eventCat":"Neutral","x":"-6.03458548","timeToReact":"99","screenV":"99","time":"20.4718361"},{"spawnID":"43","spawnType":"Bonus","eventType":"Catch","eventCat":"Positive","x":"7.4292717","timeToReact":"4.2667198","screenV":"6.41876","time":"20.4718742"},{"spawnID":"34","spawnType":"Bonus","eventType":"Miss","eventCat":"Neutral","x":"1.02127838","timeToReact":"99","screenV":"99","time":"21.05894"},{"spawnID":"35","spawnType":"Bonus","eventType":"Miss","eventCat":"Neutral","x":"-5.304659","timeToReact":"99","screenV":"99","time":"21.2592163"},{"spawnID":"37","spawnType":"Bonus","eventType":"Miss","eventCat":"Neutral","x":"0.5326537","timeToReact":"99","screenV":"99","time":"21.8947"},{"spawnID":"39","spawnType":"Obstacle","eventType":"Dodge","eventCat":"Neutral","x":"-3.94314384","timeToReact":"99","screenV":"99","time":"21.9960175"},{"spawnID":"40","spawnType":"Obstacle","eventType":"Dodge","eventCat":"Neutral","x":"-9.272704","timeToReact":"99","screenV":"99","time":"22.161171"},{"spawnID":"38","spawnType":"Bonus","eventType":"Miss","eventCat":"Neutral","x":"0.809357643","timeToReact":"99","screenV":"99","time":"22.6321"},{"spawnID":"44","spawnType":"Obstacle","eventType":"Dodge","eventCat":"Neutral","x":"13.5428085","timeToReact":"99","screenV":"99","time":"23.1695518"},{"spawnID":"46","spawnType":"Obstacle","eventType":"Dodge","eventCat":"Neutral","x":"-0.547799","timeToReact":"99","screenV":"99","time":"23.6380119"},{"spawnID":"55","spawnType":"Enemy","eventType":"Kill","eventCat":"Positive","x":"-0.369889021","timeToReact":"4.9229164","screenV":"4.72152","time":"24.2393532"},{"spawnID":"55","spawnType":"Enemy","eventType":"Hit","eventCat":"Positive","x":"-0.369889021","timeToReact":"4.9230385","screenV":"4.72140","time":"24.2394753"},{"spawnID":"48","spawnType":"Obstacle","eventType":"Dodge","eventCat":"Neutral","x":"2.62506676","timeToReact":"99","screenV":"99","time":"24.2717934"},{"spawnID":"45","spawnType":"Bonus","eventType":"Miss","eventCat":"Neutral","x":"-4.23184347","timeToReact":"99","screenV":"99","time":"24.29002"},{"spawnID":"49","spawnType":"Obstacle","eventType":"Dodge","eventCat":"Neutral","x":"11.7310448","timeToReact":"99","screenV":"99","time":"24.4220352"},{"spawnID":"58","spawnType":"Bonus","eventType":"Catch","eventCat":"Positive","x":"-4.67398","timeToReact":"4.3965486","screenV":"6.17895","time":"24.6109886"},{"spawnID":"47","spawnType":"Bonus","eventType":"Miss","eventCat":"Neutral","x":"-9.943603","timeToReact":"99","screenV":"99","time":"24.8917046"},{"spawnID":"52","spawnType":"Obstacle","eventType":"Dodge","eventCat":"Neutral","x":"-8.885161","timeToReact":"99","screenV":"99","time":"25.09093"},{"spawnID":"50","spawnType":"Enemy","eventType":"Miss","eventCat":"Neutral","x":"-14.6698647","y":"-25.1288872","timeToReact":"99","screenV":"99","time":"25.2600822"},{"spawnID":"66","spawnType":"Enemy","eventType":"Kill","eventCat":"Positive","x":"-1.71267784","timeToReact":"2.5802955","screenV":"7.17783","time":"25.2603455"},{"spawnID":"66","spawnType":"Enemy","eventType":"Hit","eventCat":"Positive","x":"-1.71267784","timeToReact":"2.58041","screenV":"7.17752","time":"25.26046"},{"spawnID":"51","spawnType":"Bonus","eventType":"Miss","eventCat":"Neutral","x":"-3.48019528","timeToReact":"99","screenV":"99","time":"25.3269272"},{"spawnID":"42","spawnType":"Enemy","eventType":"Miss","eventCat":"Neutral","x":"-10.221282","y":"-24.9321251","timeToReact":"99","screenV":"99","time":"25.5608673"},{"spawnID":"66","spawnType":"Enemy","eventType":"Hurt","eventCat":"Negative","x":"-4.90890169","timeToReact":"2.94822","screenV":"9.65099","time":"25.62827"},{"spawnID":"66","spawnType":"Enemy","eventType":"Hurt","eventCat":"Negative","x":"-4.914582","timeToReact":"2.96437","screenV":"9.59841","time":"25.64442"},{"spawnID":"66","spawnType":"Enemy","eventType":"Hurt","eventCat":"Negative","x":"-4.92284346","timeToReact":"3.0347976","screenV":"9.37566","time":"25.7148476"},{"spawnID":"66","spawnType":"Enemy","eventType":"Hurt","eventCat":"Negative","x":"-4.92192936","timeToReact":"3.0555076","screenV":"9.31212","time":"25.7355576"},{"spawnID":"66","spawnType":"Enemy","eventType":"Hurt","eventCat":"Negative","x":"-4.910864","timeToReact":"3.0970229","screenV":"9.18729","time":"25.7770729"},{"spawnID":"66","spawnType":"Enemy","eventType":"Hurt","eventCat":"Negative","x":"-4.893275","timeToReact":"3.1306533","screenV":"9.08860","time":"25.8107033"},{"spawnID":"56","spawnType":"Obstacle","eventType":"Dodge","eventCat":"Neutral","x":"12.5294838","timeToReact":"99","screenV":"99","time":"26.2953835"},{"spawnID":"53","spawnType":"Bonus","eventType":"Miss","eventCat":"Neutral","x":"-7.69261551","timeToReact":"99","screenV":"99","time":"26.3576736"},{"spawnID":"54","spawnType":"Bonus","eventType":"Miss","eventCat":"Neutral","x":"-7.683766","timeToReact":"99","screenV":"99","time":"26.49823"},{"spawnID":"59","spawnType":"Obstacle","eventType":"Dodge","eventCat":"Neutral","x":"8.710869","timeToReact":"99","screenV":"99","time":"27.19933"},{"spawnID":"57","spawnType":"Bonus","eventType":"Miss","eventCat":"Neutral","x":"-10.008152","timeToReact":"99","screenV":"99","time":"27.2398911"},{"spawnID":"60","spawnType":"Bonus","eventType":"Miss","eventCat":"Neutral","x":"6.33127069","timeToReact":"99","screenV":"99","time":"28.2379341"},{"spawnID":"64","spawnType":"Obstacle","eventType":"Dodge","eventCat":"Neutral","x":"-10.6412125","timeToReact":"99","screenV":"99","time":"28.7911835"},{"spawnID":"62","spawnType":"Bonus","eventType":"Miss","eventCat":"Neutral","x":"-11.5301552","timeToReact":"99","screenV":"99","time":"28.9262543"},{"spawnID":"72","spawnType":"Bonus","eventType":"Catch","eventCat":"Positive","x":"-6.80251837","timeToReact":"4.1750679","screenV":"6.73770","time":"28.9766922"},{"spawnID":"70","spawnType":"Enemy","eventType":"Kill","eventCat":"Positive","x":"-7.90734959","timeToReact":"4.9428253","screenV":"4.72030","time":"29.3122215"},{"spawnID":"70","spawnType":"Enemy","eventType":"Hit","eventCat":"Positive","x":"-7.90734959","timeToReact":"4.9428558","screenV":"4.72027","time":"29.312252"},{"spawnID":"63","spawnType":"Bonus","eventType":"Miss","eventCat":"Neutral","x":"9.675822","timeToReact":"99","screenV":"99","time":"29.4120865"},{"spawnID":"65","spawnType":"Bonus","eventType":"Miss","eventCat":"Neutral","x":"6.98686552","timeToReact":"99","screenV":"99","time":"29.8284912"},{"spawnID":"74","spawnType":"Bonus","eventType":"Catch","eventCat":"Positive","x":"5.664776","timeToReact":"4.2826048","screenV":"6.38941","time":"30.19587"},{"spawnID":"73","spawnType":"Bonus","eventType":"Catch","eventCat":"Positive","x":"9.217393","timeToReact":"5.0851097","screenV":"5.51497","time":"30.4333725"},{"spawnID":"75","spawnType":"Enemy","eventType":"Collision","eventCat":"Negative","x":"13.0833588","y":"-6.47112942","timeToReact":"4.5275727","screenV":"5.96803","time":"30.5646439"},{"spawnID":"75","spawnType":"Enemy","eventType":"Hurt","eventCat":"Negative","x":"10.923172","timeToReact":"4.5460968","screenV":"6.25883","time":"30.583168"},{"spawnID":"67","spawnType":"Bonus","eventType":"Miss","eventCat":"Neutral","x":"-9.071724","timeToReact":"99","screenV":"99","time":"30.6154327"},{"spawnID":"61","spawnType":"Enemy","eventType":"Miss","eventCat":"Neutral","x":"13.7139416","y":"-24.9006233","timeToReact":"99","screenV":"99","time":"30.6154556"},{"spawnID":"68","spawnType":"Bonus","eventType":"Miss","eventCat":"Neutral","x":"11.2146139","timeToReact":"99","screenV":"99","time":"31.23479"},{"spawnID":"71","spawnType":"Obstacle","eventType":"Dodge","eventCat":"Neutral","x":"6.834215","timeToReact":"99","screenV":"99","time":"31.353157"},{"spawnID":"76","spawnType":"Bonus","eventType":"Catch","eventCat":"Positive","x":"8.286104","timeToReact":"4.9870749","screenV":"5.71788","time":"31.4674149"},{"spawnID":"69","spawnType":"Bonus","eventType":"Miss","eventCat":"Neutral","x":"4.19720125","timeToReact":"99","screenV":"99","time":"31.83818"},{"spawnID":"78","spawnType":"Bonus","eventType":"Catch","eventCat":"Positive","x":"-9.2837925","timeToReact":"4.9039387","screenV":"5.91535","time":"32.5229"},{"spawnID":"81","spawnType":"Obstacle","eventType":"Collision","eventCat":"Negative","x":"-12.2662964","timeToReact":"4.36739","screenV":"5.96565","time":"32.64011"},{"spawnID":"84","spawnType":"Enemy","eventType":"Kill","eventCat":"Positive","x":"-5.95711946","timeToReact":"3.6857723","screenV":"4.76610","time":"33.09071"},{"spawnID":"84","spawnType":"Enemy","eventType":"Hit","eventCat":"Positive","x":"-5.95711946","timeToReact":"3.6857987","screenV":"4.76607","time":"33.0907364"},{"spawnID":"82","spawnType":"Bonus","eventType":"Catch","eventCat":"Positive","x":"-0.229818523","timeToReact":"4.7747193","screenV":"6.01002","time":"33.5447922"},{"spawnID":"83","spawnType":"Bonus","eventType":"Catch","eventCat":"Positive","x":"3.21959376","timeToReact":"4.4111447","screenV":"6.19324","time":"33.74614"},{"spawnID":"85","spawnType":"Bonus","eventType":"Catch","eventCat":"Positive","x":"10.8648129","timeToReact":"4.2570458","screenV":"6.19675","time":"34.1615639"},{"spawnID":"77","spawnType":"Bonus","eventType":"Miss","eventCat":"Neutral","x":"-14.79817","timeToReact":"99","screenV":"99","time":"34.7501869"},{"spawnID":"81","spawnType":"Obstacle","eventType":"Dodge","eventCat":"Neutral","x":"-12.2662964","timeToReact":"99","screenV":"99","time":"35.0312653"},{"spawnID":"80","spawnType":"Bonus","eventType":"Miss","eventCat":"Neutral","x":"9.64764","timeToReact":"99","screenV":"99","time":"35.6755"},{"spawnID":"79","spawnType":"Enemy","eventType":"Miss","eventCat":"Neutral","x":"15.7507448","y":"-24.89357","timeToReact":"99","screenV":"99","time":"37.32584"},{"spawnID":"87","spawnType":"Obstacle","eventType":"Collision","eventCat":"Negative","x":"9.870594","timeToReact":"4.2483464","screenV":"5.95613","time":"45.1237564"},{"spawnID":"90","spawnType":"Bonus","eventType":"Catch","eventCat":"Positive","x":"8.051416","timeToReact":"5.1097057","screenV":"5.45018","time":"46.81861"},{"spawnID":"92","spawnType":"Bonus","eventType":"Catch","eventCat":"Positive","x":"5.770869","timeToReact":"4.1981327","screenV":"6.73901","time":"47.0328827"},{"spawnID":"93","spawnType":"Obstacle","eventType":"Collision","eventCat":"Negative","x":"-2.26601219","timeToReact":"4.29176","screenV":"5.95887","time":"47.57379"},{"spawnID":"87","spawnType":"Obstacle","eventType":"Dodge","eventCat":"Neutral","x":"9.870594","timeToReact":"99","screenV":"99","time":"47.70195"},{"spawnID":"91","spawnType":"Bonus","eventType":"Catch","eventCat":"Positive","x":"-4.419515","timeToReact":"5.5983887","screenV":"5.22527","time":"47.8715363"},{"spawnID":"95","spawnType":"Bonus","eventType":"Catch","eventCat":"Positive","x":"-4.878071","timeToReact":"4.4844731","screenV":"6.72723","time":"47.9026031"},{"spawnID":"86","spawnType":"Bonus","eventType":"Miss","eventCat":"Neutral","x":"-11.6670532","timeToReact":"99","screenV":"99","time":"48.07119"},{"spawnID":"97","spawnType":"Bonus","eventType":"Catch","eventCat":"Positive","x":"-9.58354","timeToReact":"4.3875259","screenV":"6.27917","time":"48.3709259"},{"spawnID":"88","spawnType":"Bonus","eventType":"Miss","eventCat":"Neutral","x":"-1.60212421","timeToReact":"99","screenV":"99","time":"48.68763"},{"spawnID":"98","spawnType":"Bonus","eventType":"Catch","eventCat":"Positive","x":"-7.34914064","timeToReact":"4.1171339","screenV":"6.54803","time":"48.68766"},{"spawnID":"89","spawnType":"Enemy","eventType":"Hurt","eventCat":"Negative","x":"-7.06412458","timeToReact":"7.05092","screenV":"4.03539","time":"48.72323"},{"spawnID":"100","spawnType":"Bonus","eventType":"Catch","eventCat":"Positive","x":"-3.46203637","timeToReact":"4.0887541","screenV":"6.69796","time":"49.22516"},{"spawnID":"93","spawnType":"Obstacle","eventType":"Dodge","eventCat":"Neutral","x":"-2.26601219","timeToReact":"99","screenV":"99","time":"50.095932"},{"spawnID":"96","spawnType":"Obstacle","eventType":"Dodge","eventCat":"Neutral","x":"3.24588966","timeToReact":"99","screenV":"99","time":"50.31311"},{"spawnID":"99","spawnType":"Enemy","eventType":"Hurt","eventCat":"Negative","x":"10.2464809","timeToReact":"5.3408127","screenV":"5.32751","time":"50.3820267"},{"spawnID":"99","spawnType":"Enemy","eventType":"Collision","eventCat":"Negative","x":"8.936317","y":"-4.73168373","timeToReact":"5.3761825","screenV":"4.70245","time":"50.4173965"},{"spawnID":"103","spawnType":"Bonus","eventType":"Catch","eventCat":"Positive","x":"4.08058834","timeToReact":"4.3814249","screenV":"6.15081","time":"50.6549149"},{"spawnID":"99","spawnType":"Enemy","eventType":"Hurt","eventCat":"Negative","x":"4.92528963","timeToReact":"5.6448135","screenV":"5.04060","time":"50.6860275"},{"spawnID":"104","spawnType":"Enemy","eventType":"Kill","eventCat":"Positive","x":"12.6003962","timeToReact":"4.0444734","screenV":"5.04998","time":"50.75403"},{"spawnID":"104","spawnType":"Enemy","eventType":"Hit","eventCat":"Positive","x":"12.6003962","timeToReact":"4.0445234","screenV":"5.04992","time":"50.75408"},{"spawnID":"102","spawnType":"Bonus","eventType":"Catch","eventCat":"Positive","x":"-0.683893859","timeToReact":"5.2794190","screenV":"5.55465","time":"50.9846039"},{"spawnID":"106","spawnType":"Bonus","eventType":"Catch","eventCat":"Positive","x":"-1.6956358","timeToReact":"4.3460006","screenV":"6.67439","time":"51.1652374"},{"spawnID":"89","spawnType":"Enemy","eventType":"Miss","eventCat":"Neutral","x":"-12.986805","y":"-24.9085732","timeToReact":"99","screenV":"99","time":"51.2996"},{"spawnID":"101","spawnType":"Obstacle","eventType":"Dodge","eventCat":"Neutral","x":"-8.316279","timeToReact":"99","screenV":"99","time":"52.18676"},{"spawnID":"105","spawnType":"Obstacle","eventType":"Dodge","eventCat":"Neutral","x":"14.285553","timeToReact":"99","screenV":"99","time":"53.6266022"},{"spawnID":"107","spawnType":"Obstacle","eventType":"Dodge","eventCat":"Neutral","x":"-8.416827","timeToReact":"99","screenV":"99","time":"53.8606949"},{"spawnID":"112","spawnType":"Bonus","eventType":"Catch","eventCat":"Positive","x":"10.1064367","timeToReact":"5.330164","screenV":"5.42571","time":"53.893364"},{"spawnID":"115","spawnType":"Bonus","eventType":"Catch","eventCat":"Positive","x":"4.58282661","timeToReact":"4.5884171","screenV":"6.14146","time":"54.2949371"},{"spawnID":"109","spawnType":"Obstacle","eventType":"Dodge","eventCat":"Neutral","x":"-9.798526","timeToReact":"99","screenV":"99","time":"54.5629578"},{"spawnID":"108","spawnType":"Bonus","eventType":"Miss","eventCat":"Neutral","x":"-12.1071615","timeToReact":"99","screenV":"99","time":"54.9324341"},{"spawnID":"110","spawnType":"Bonus","eventType":"Miss","eventCat":"Neutral","x":"-13.3344488","timeToReact":"99","screenV":"99","time":"55.4664764"},{"spawnID":"117","spawnType":"Enemy","eventType":"Hurt","eventCat":"Negative","x":"6.10839224","timeToReact":"5.4646671","screenV":"5.20677","time":"55.5368271"},{"spawnID":"117","spawnType":"Enemy","eventType":"Hurt","eventCat":"Negative","x":"6.35483265","timeToReact":"5.5329578","screenV":"5.14250","time":"55.6051178"},{"spawnID":"117","spawnType":"Enemy","eventType":"Hurt","eventCat":"Negative","x":"6.57380962","timeToReact":"5.59932","screenV":"5.08155","time":"55.67148"},{"spawnID":"117","spawnType":"Enemy","eventType":"Hurt","eventCat":"Negative","x":"6.68414736","timeToReact":"5.6291645","screenV":"5.05461","time":"55.7013245"},{"spawnID":"117","spawnType":"Enemy","eventType":"Hurt","eventCat":"Negative","x":"6.90635252","timeToReact":"5.7329471","screenV":"4.96311","time":"55.8051071"},{"spawnID":"117","spawnType":"Enemy","eventType":"Collision","eventCat":"Negative","x":"8.892449","y":"-6.268597","timeToReact":"5.7332828","screenV":"4.67763","time":"55.8054428"},{"spawnID":"114","spawnType":"Obstacle","eventType":"Dodge","eventCat":"Neutral","x":"-5.76665","timeToReact":"99","screenV":"99","time":"55.9677277"},{"spawnID":"126","spawnType":"Bonus","eventType":"Catch","eventCat":"Positive","x":"5.47429943","timeToReact":"4.0071656","screenV":"6.76099","time":"56.5557556"},{"spawnID":"116","spawnType":"Obstacle","eventType":"Dodge","eventCat":"Neutral","x":"-9.352618","timeToReact":"99","screenV":"99","time":"56.72074"},{"spawnID":"113","spawnType":"Bonus","eventType":"Miss","eventCat":"Neutral","x":"-10.921607","timeToReact":"99","screenV":"99","time":"56.756134"},{"spawnID":"118","spawnType":"Bonus","eventType":"Miss","eventCat":"Neutral","x":"-11.584446","timeToReact":"99","screenV":"99","time":"57.6920547"},{"spawnID":"111","spawnType":"Enemy","eventType":"Miss","eventCat":"Neutral","x":"-15.28124","y":"-24.98189","timeToReact":"99","screenV":"99","time":"58.0165634"},{"spawnID":"121","spawnType":"Obstacle","eventType":"Dodge","eventCat":"Neutral","x":"14.5260086","timeToReact":"99","screenV":"99","time":"58.0610733"},{"spawnID":"119","spawnType":"Bonus","eventType":"Miss","eventCat":"Neutral","x":"-11.730588","timeToReact":"99","screenV":"99","time":"58.1948242"},{"spawnID":"120","spawnType":"Obstacle","eventType":"Dodge","eventCat":"Neutral","x":"-11.6191921","timeToReact":"99","screenV":"99","time":"58.2473068"},{"spawnID":"123","spawnType":"Obstacle","eventType":"Dodge","eventCat":"Neutral","x":"-4.701766","timeToReact":"99","screenV":"99","time":"58.3284149"},{"spawnID":"122","spawnType":"Bonus","eventType":"Miss","eventCat":"Neutral","x":"0.6251242","timeToReact":"99","screenV":"99","time":"58.7293243"},{"spawnID":"133","spawnType":"Enemy","eventType":"Hurt","eventCat":"Negative","x":"4.617138","timeToReact":"5.7270671","screenV":"4.96820","time":"59.1653671"},{"spawnID":"127","spawnType":"Bonus","eventType":"Miss","eventCat":"Neutral","x":"-12.6159315","timeToReact":"99","screenV":"99","time":"59.18312"},{"spawnID":"130","spawnType":"Bonus","eventType":"Miss","eventCat":"Neutral","x":"-10.1255865","timeToReact":"99","screenV":"99","time":"59.183136"},{"spawnID":"131","spawnType":"Bonus","eventType":"Miss","eventCat":"Neutral","x":"-10.1200714","timeToReact":"99","screenV":"99","time":"59.2510147"},{"spawnID":"128","spawnType":"Bonus","eventType":"Miss","eventCat":"Neutral","x":"-10.56136","timeToReact":"99","screenV":"99","time":"59.3253479"},{"spawnID":"133","spawnType":"Enemy","eventType":"Hurt","eventCat":"Negative","x":"5.26049328","timeToReact":"5.8878948","screenV":"4.83250","time":"59.3261948"},{"spawnID":"129","spawnType":"Bonus","eventType":"Miss","eventCat":"Neutral","x":"-11.5045166","timeToReact":"99","screenV":"99","time":"59.3448334"},{"spawnID":"138","spawnType":"Bonus","eventType":"Catch","eventCat":"Positive","x":"4.437955","timeToReact":"4.5424261","screenV":"6.30440","time":"59.3847961"},{"spawnID":"133","spawnType":"Enemy","eventType":"Hurt","eventCat":"Negative","x":"5.9598403","timeToReact":"5.9965145","screenV":"4.74496","time":"59.4348145"},{"spawnID":"133","spawnType":"Enemy","eventType":"Hurt","eventCat":"Negative","x":"7.108701","timeToReact":"6.1625453","screenV":"4.61712","time":"59.6008453"},{"spawnID":"133","spawnType":"Enemy","eventType":"Hurt","eventCat":"Negative","x":"7.633453","timeToReact":"6.2290965","screenV":"4.56780","time":"59.6673965"},{"spawnID":"133","spawnType":"Enemy","eventType":"Hurt","eventCat":"Negative","x":"7.633453","timeToReact":"6.2291728","screenV":"4.56774","time":"59.6674728"},{"spawnID":"133","spawnType":"Enemy","eventType":"Hurt","eventCat":"Negative","x":"7.633453","timeToReact":"6.22921","screenV":"4.56771","time":"59.66751"},{"spawnID":"125","spawnType":"Bonus","eventType":"Miss","eventCat":"Neutral","x":"11.8046789","timeToReact":"99","screenV":"99","time":"59.6675339"},{"spawnID":"133","spawnType":"Enemy","eventType":"Collision","eventCat":"Negative","x":"9.938962","y":"-8.616007","timeToReact":"6.22953","screenV":"4.68183","time":"59.66783"},{"spawnID":"141","spawnType":"Bonus","eventType":"Catch","eventCat":"Positive","x":"10.802619","timeToReact":"4.1195144","screenV":"6.39810","time":"60.102478"},{"spawnID":"144","spawnType":"Enemy","eventType":"Hurt","eventCat":"Negative","x":"10.4837875","timeToReact":"3.47080","screenV":"8.19789","time":"60.27088"},{"spawnID":"144","spawnType":"Enemy","eventType":"Hurt","eventCat":"Negative","x":"10.4968185","timeToReact":"3.4914773","screenV":"8.14934","time":"60.2915573"},{"spawnID":"144","spawnType":"Enemy","eventType":"Hurt","eventCat":"Negative","x":"10.4968185","timeToReact":"3.491546","screenV":"8.14918","time":"60.291626"},{"spawnID":"144","spawnType":"Enemy","eventType":"Hurt","eventCat":"Negative","x":"10.4771566","timeToReact":"3.5924371","screenV":"7.92032","time":"60.3925171"},{"spawnID":"144","spawnType":"Enemy","eventType":"Collision","eventCat":"Negative","x":"11.6836061","y":"-5.33070469","timeToReact":"3.59278","screenV":"7.20341","time":"60.39286"},{"spawnID":"132","spawnType":"Bonus","eventType":"Miss","eventCat":"Neutral","x":"11.2237711","timeToReact":"99","screenV":"99","time":"60.72152"},{"spawnID":"136","spawnType":"Obstacle","eventType":"Dodge","eventCat":"Neutral","x":"11.254982","timeToReact":"99","screenV":"99","time":"60.82361"},{"spawnID":"135","spawnType":"Obstacle","eventType":"Dodge","eventCat":"Neutral","x":"-8.106095","timeToReact":"99","screenV":"99","time":"60.88978"},{"spawnID":"134","spawnType":"Bonus","eventType":"Miss","eventCat":"Neutral","x":"-4.941499","timeToReact":"99","screenV":"99","time":"61.2234344"},{"spawnID":"145","spawnType":"Bonus","eventType":"Catch","eventCat":"Positive","x":"12.7579765","timeToReact":"4.2208646","screenV":"6.67183","time":"61.35724"},{"spawnID":"137","spawnType":"Bonus","eventType":"Miss","eventCat":"Neutral","x":"-11.3795118","timeToReact":"99","screenV":"99","time":"61.79312"},{"spawnID":"140","spawnType":"Bonus","eventType":"Miss","eventCat":"Neutral","x":"-2.60985541","timeToReact":"99","screenV":"99","time":"62.7295532"},{"spawnID":"139","spawnType":"Enemy","eventType":"Miss","eventCat":"Neutral","x":"-1.79328728","y":"-25.2350655","timeToReact":"99","screenV":"99","time":"62.764946"},{"spawnID":"148","spawnType":"Bonus","eventType":"Catch","eventCat":"Positive","x":"1.16514039","timeToReact":"5.7625962","screenV":"5.39049","time":"63.46624"},{"spawnID":"153","spawnType":"Bonus","eventType":"Catch","eventCat":"Positive","x":"1.58839726","timeToReact":"4.1634752","screenV":"6.60387","time":"63.5729752"},{"spawnID":"143","spawnType":"Obstacle","eventType":"Dodge","eventCat":"Neutral","x":"-3.48758125","timeToReact":"99","screenV":"99","time":"63.5991821"},{"spawnID":"151","spawnType":"Bonus","eventType":"Catch","eventCat":"Positive","x":"-0.20245719","timeToReact":"4.8269356","screenV":"5.81272","time":"63.66726"},{"spawnID":"142","spawnType":"Bonus","eventType":"Miss","eventCat":"Neutral","x":"-0.52476275","timeToReact":"99","screenV":"99","time":"63.98456"},{"spawnID":"146","spawnType":"Obstacle","eventType":"Dodge","eventCat":"Neutral","x":"-7.51826763","timeToReact":"99","screenV":"99","time":"64.1359253"},{"spawnID":"152","spawnType":"Obstacle","eventType":"Collision","eventCat":"Negative","x":"7.29288673","timeToReact":"4.8451614","screenV":"5.99262","time":"64.2528839"},{"spawnID":"147","spawnType":"Obstacle","eventType":"Dodge","eventCat":"Neutral","x":"1.81391716","timeToReact":"99","screenV":"99","time":"64.35297"},{"spawnID":"156","spawnType":"Bonus","eventType":"Catch","eventCat":"Positive","x":"5.47932434","timeToReact":"3.8315834","screenV":"6.78316","time":"64.37118"},{"spawnID":"154","spawnType":"Bonus","eventType":"Catch","eventCat":"Positive","x":"8.194429","timeToReact":"4.3915406","screenV":"6.02448","time":"64.371254"},{"spawnID":"149","spawnType":"Bonus","eventType":"Miss","eventCat":"Neutral","x":"-8.188308","timeToReact":"99","screenV":"99","time":"65.92592"},{"spawnID":"150","spawnType":"Enemy","eventType":"Miss","eventCat":"Neutral","x":"-7.79415035","y":"-25.2293549","timeToReact":"99","screenV":"99","time":"66.12769"},{"spawnID":"152","spawnType":"Obstacle","eventType":"Dodge","eventCat":"Neutral","x":"7.29288673","timeToReact":"99","screenV":"99","time":"66.22648"},{"spawnID":"155","spawnType":"Enemy","eventType":"Miss","eventCat":"Neutral","x":"-6.750787","y":"-25.0689144","timeToReact":"99","screenV":"99","time":"66.4278641"},{"spawnID":"160","spawnType":"Bonus","eventType":"Catch","eventCat":"Positive","x":"4.4408493","timeToReact":"4.3497828","screenV":"6.66732","time":"66.62969"},{"spawnID":"161","spawnType":"Bonus","eventType":"Catch","eventCat":"Positive","x":"9.273651","timeToReact":"4.9822968","screenV":"5.79477","time":"67.81577"},{"spawnID":"157","spawnType":"Bonus","eventType":"Miss","eventCat":"Neutral","x":"-7.091076","timeToReact":"99","screenV":"99","time":"68.7727051"},{"spawnID":"158","spawnType":"Bonus","eventType":"Miss","eventCat":"Neutral","x":"-11.2728786","timeToReact":"99","screenV":"99","time":"69.28977"},{"spawnID":"173","spawnType":"Bonus","eventType":"Catch","eventCat":"Positive","x":"15.5712862","timeToReact":"4.61987","screenV":"6.14647","time":"70.29386"},{"spawnID":"175","spawnType":"Bonus","eventType":"Catch","eventCat":"Positive","x":"15.395071","timeToReact":"4.29579","screenV":"6.42709","time":"70.53588"},{"spawnID":"162","spawnType":"Bonus","eventType":"Miss","eventCat":"Neutral","x":"-5.35884571","timeToReact":"99","screenV":"99","time":"70.71441"},{"spawnID":"164","spawnType":"Obstacle","eventType":"Dodge","eventCat":"Neutral","x":"-15.0186768","timeToReact":"99","screenV":"99","time":"70.79638"},{"spawnID":"177","spawnType":"Bonus","eventType":"Catch","eventCat":"Positive","x":"10.8794031","timeToReact":"4.12364","screenV":"6.31889","time":"70.93214"},{"spawnID":"165","spawnType":"Bonus","eventType":"Miss","eventCat":"Neutral","x":"-2.691601","timeToReact":"99","screenV":"99","time":"71.23217"},{"spawnID":"166","spawnType":"Obstacle","eventType":"Dodge","eventCat":"Neutral","x":"-5.67599","timeToReact":"99","screenV":"99","time":"71.29855"},{"spawnID":"168","spawnType":"Obstacle","eventType":"Dodge","eventCat":"Neutral","x":"-1.35450172","timeToReact":"99","screenV":"99","time":"71.36461"},{"spawnID":"159","spawnType":"Enemy","eventType":"Miss","eventCat":"Neutral","x":"-9.1235075","y":"-24.897644","timeToReact":"99","screenV":"99","time":"71.46596"},{"spawnID":"179","spawnType":"Bonus","eventType":"Catch","eventCat":"Positive","x":"5.177304","timeToReact":"4.30366","screenV":"6.33038","time":"71.66747"},{"spawnID":"169","spawnType":"Obstacle","eventType":"Dodge","eventCat":"Neutral","x":"13.0775528","timeToReact":"99","screenV":"99","time":"71.73315"},{"spawnID":"167","spawnType":"Bonus","eventType":"Miss","eventCat":"Neutral","x":"-8.049822","timeToReact":"99","screenV":"99","time":"71.77268"},{"spawnID":"170","spawnType":"Obstacle","eventType":"Dodge","eventCat":"Neutral","x":"0.3983364","timeToReact":"99","screenV":"99","time":"71.90019"},{"spawnID":"180","spawnType":"Bonus","eventType":"Catch","eventCat":"Positive","x":"5.20983744","timeToReact":"4.05671","screenV":"6.58425","time":"72.00338"},{"spawnID":"171","spawnType":"Bonus","eventType":"Miss","eventCat":"Neutral","x":"-5.221984","timeToReact":"99","screenV":"99","time":"72.63869"},{"spawnID":"174","spawnType":"Obstacle","eventType":"Dodge","eventCat":"Neutral","x":"5.010721","timeToReact":"99","screenV":"99","time":"72.87214"},{"spawnID":"176","spawnType":"Obstacle","eventType":"Dodge","eventCat":"Neutral","x":"-4.68233","timeToReact":"99","screenV":"99","time":"73.47312"},{"spawnID":"181","spawnType":"Obstacle","eventType":"Dodge","eventCat":"Neutral","x":"0.6743145","timeToReact":"99","screenV":"99","time":"75.38378"},{"spawnID":"182","spawnType":"Bonus","eventType":"Miss","eventCat":"Neutral","x":"-2.26413965","timeToReact":"99","screenV":"99","time":"75.90153"},{"spawnID":"184","spawnType":"Bonus","eventType":"Miss","eventCat":"Neutral","x":"3.363706","timeToReact":"99","screenV":"99","time":"76.43751"},{"spawnID":"185","spawnType":"Bonus","eventType":"Miss","eventCat":"Neutral","x":"-1.12244916","timeToReact":"99","screenV":"99","time":"77.1579361"},{"spawnID":"183","spawnType":"Enemy","eventType":"Miss","eventCat":"Neutral","x":"-13.9080334","y":"-24.8800354","timeToReact":"99","screenV":"99","time":"78.16181"},{"spawnID":"188","spawnType":"Enemy","eventType":"Hit","eventCat":"Positive","x":"7.56633568","timeToReact":"2.5306254","screenV":"5.95030","time":"84.20115"},{"spawnID":"188","spawnType":"Enemy","eventType":"Kill","eventCat":"Positive","x":"7.56633568","timeToReact":"3.0184708","screenV":"5.98484","time":"84.6889954"},{"spawnID":"188","spawnType":"Enemy","eventType":"Hit","eventCat":"Positive","x":"7.56633568","timeToReact":"3.0186154","screenV":"5.98455","time":"84.68914"},{"spawnID":"186","spawnType":"Bonus","eventType":"Catch","eventCat":"Positive","x":"-7.388595","timeToReact":"4.5875256","screenV":"6.26381","time":"85.155"},{"spawnID":"189","spawnType":"Bonus","eventType":"Catch","eventCat":"Positive","x":"-1.718988","timeToReact":"4.25221","screenV":"6.58286","time":"85.95515"},{"spawnID":"187","spawnType":"Bonus","eventType":"Catch","eventCat":"Positive","x":"1.43155038","timeToReact":"4.8241449","screenV":"5.93419","time":"85.95534"},{"spawnID":"197","spawnType":"Bonus","eventType":"Catch","eventCat":"Positive","x":"6.629563","timeToReact":"4.3292008","screenV":"6.35981","time":"88.305275"},{"spawnID":"191","spawnType":"Obstacle","eventType":"Dodge","eventCat":"Neutral","x":"9.143719","timeToReact":"99","screenV":"99","time":"89.15469"},{"spawnID":"198","spawnType":"Bonus","eventType":"Catch","eventCat":"Positive","x":"-0.152341187","timeToReact":"4.8840485","screenV":"5.89161","time":"89.4238739"},{"spawnID":"200","spawnType":"Bonus","eventType":"Catch","eventCat":"Positive","x":"-2.835527","timeToReact":"4.4833856","screenV":"6.06940","time":"89.59199"},{"spawnID":"190","spawnType":"Bonus","eventType":"Miss","eventCat":"Neutral","x":"-5.133019","timeToReact":"99","screenV":"99","time":"89.76041"},{"spawnID":"203","spawnType":"Bonus","eventType":"Catch","eventCat":"Positive","x":"-3.93652582","timeToReact":"4.1876059","screenV":"6.49580","time":"89.8912659"},{"spawnID":"192","spawnType":"Bonus","eventType":"Miss","eventCat":"Neutral","x":"1.5009855","timeToReact":"99","screenV":"99","time":"90.33086"},{"spawnID":"196","spawnType":"Obstacle","eventType":"Dodge","eventCat":"Neutral","x":"-5.574374","timeToReact":"99","screenV":"99","time":"90.4887848"},{"spawnID":"195","spawnType":"Obstacle","eventType":"Dodge","eventCat":"Neutral","x":"1.227471","timeToReact":"99","screenV":"99","time":"90.544075"},{"spawnID":"204","spawnType":"Bonus","eventType":"Catch","eventCat":"Positive","x":"0.217392862","timeToReact":"4.55881","screenV":"6.06586","time":"90.83039"},{"spawnID":"194","spawnType":"Bonus","eventType":"Miss","eventCat":"Neutral","x":"-2.19451761","timeToReact":"99","screenV":"99","time":"90.8624344"},{"spawnID":"199","spawnType":"Enemy","eventType":"Hurt","eventCat":"Negative","x":"10.3724909","timeToReact":"6.4911451","screenV":"4.38339","time":"91.49895"},{"spawnID":"199","spawnType":"Enemy","eventType":"Hurt","eventCat":"Negative","x":"10.3724909","timeToReact":"6.4913551","screenV":"4.38325","time":"91.49916"},{"spawnID":"199","spawnType":"Enemy","eventType":"Hurt","eventCat":"Negative","x":"10.3724909","timeToReact":"6.4915251","screenV":"4.38314","time":"91.49933"},{"spawnID":"199","spawnType":"Enemy","eventType":"Hurt","eventCat":"Negative","x":"10.3724909","timeToReact":"6.4915751","screenV":"4.38310","time":"91.49938"},{"spawnID":"199","spawnType":"Enemy","eventType":"Hurt","eventCat":"Negative","x":"10.7289228","timeToReact":"6.5246251","screenV":"4.36090","time":"91.53243"},{"spawnID":"199","spawnType":"Enemy","eventType":"Hurt","eventCat":"Negative","x":"11.075613","timeToReact":"6.5576851","screenV":"4.33892","time":"91.56549"},{"spawnID":"199","spawnType":"Enemy","eventType":"Hurt","eventCat":"Negative","x":"11.3935328","timeToReact":"6.5928151","screenV":"4.31580","time":"91.60062"},{"spawnID":"199","spawnType":"Enemy","eventType":"Hurt","eventCat":"Negative","x":"11.7065344","timeToReact":"6.6258392","screenV":"4.29428","time":"91.6336441"},{"spawnID":"208","spawnType":"Obstacle","eventType":"Collision","eventCat":"Negative","x":"13.9811134","timeToReact":"4.29158","screenV":"5.96804","time":"91.66771"},{"spawnID":"209","spawnType":"Bonus","eventType":"Catch","eventCat":"Positive","x":"12.1874924","timeToReact":"4.34043","screenV":"6.32593","time":"91.75299"},{"spawnID":"199","spawnType":"Enemy","eventType":"Hurt","eventCat":"Negative","x":"12.7961769","timeToReact":"6.7640151","screenV":"4.20656","time":"91.77182"},{"spawnID":"201","spawnType":"Obstacle","eventType":"Dodge","eventCat":"Neutral","x":"-15.3851776","timeToReact":"99","screenV":"99","time":"91.96568"},{"spawnID":"211","spawnType":"Enemy","eventType":"Kill","eventCat":"Positive","x":"6.21101665","timeToReact":"3.6282254","screenV":"4.71911","time":"92.0060654"},{"spawnID":"211","spawnType":"Enemy","eventType":"Hit","eventCat":"Positive","x":"6.21101665","timeToReact":"3.6282559","screenV":"4.71907","time":"92.0060959"},{"spawnID":"199","spawnType":"Enemy","eventType":"Hurt","eventCat":"Negative","x":"12.208786","timeToReact":"7.1989151","screenV":"3.95243","time":"92.20672"},{"spawnID":"199","spawnType":"Enemy","eventType":"Hurt","eventCat":"Negative","x":"11.4621506","timeToReact":"7.2634201","screenV":"3.91733","time":"92.271225"},{"spawnID":"202","spawnType":"Obstacle","eventType":"Dodge","eventCat":"Neutral","x":"4.95749855","timeToReact":"99","screenV":"99","time":"92.33723"},{"spawnID":"199","spawnType":"Enemy","eventType":"Hurt","eventCat":"Negative","x":"9.748388","timeToReact":"7.3628251","screenV":"3.86445","time":"92.37063"},{"spawnID":"205","spawnType":"Enemy","eventType":"Hurt","eventCat":"Negative","x":"7.97740364","timeToReact":"5.7580719","screenV":"4.94145","time":"92.470726"},{"spawnID":"199","spawnType":"Enemy","eventType":"Hurt","eventCat":"Negative","x":"7.97740364","timeToReact":"7.4634851","screenV":"3.81233","time":"92.47129"},{"spawnID":"205","spawnType":"Enemy","eventType":"Hurt","eventCat":"Negative","x":"7.33345175","timeToReact":"5.7900259","screenV":"4.91418","time":"92.50268"},{"spawnID":"205","spawnType":"Enemy","eventType":"Hurt","eventCat":"Negative","x":"6.73990345","timeToReact":"5.8262100","screenV":"4.88366","time":"92.5388641"},{"spawnID":"205","spawnType":"Enemy","eventType":"Hurt","eventCat":"Negative","x":"6.052858","timeToReact":"5.8571259","screenV":"4.85788","time":"92.56978"},{"spawnID":"210","spawnType":"Bonus","eventType":"Catch","eventCat":"Positive","x":"4.0472374","timeToReact":"4.59750","screenV":"6.05089","time":"92.56984"},{"spawnID":"205","spawnType":"Enemy","eventType":"Hurt","eventCat":"Negative","x":"5.46866131","timeToReact":"5.8933159","screenV":"4.82805","time":"92.60597"},{"spawnID":"205","spawnType":"Enemy","eventType":"Hurt","eventCat":"Negative","x":"4.172201","timeToReact":"5.9587959","screenV":"4.77500","time":"92.67145"},{"spawnID":"205","spawnType":"Enemy","eventType":"Collision","eventCat":"Negative","x":"1.24663","y":"-7.34474754","timeToReact":"5.9591659","screenV":"4.68091","time":"92.67182"},{"spawnID":"205","spawnType":"Enemy","eventType":"Hurt","eventCat":"Negative","x":"4.172201","timeToReact":"5.9598559","screenV":"4.77415","time":"92.67251"},{"spawnID":"193","spawnType":"Enemy","eventType":"Miss","eventCat":"Neutral","x":"15.998126","y":"-24.9117069","timeToReact":"99","screenV":"99","time":"92.95361"},{"spawnID":"213","spawnType":"Obstacle","eventType":"Collision","eventCat":"Negative","x":"-3.1296978","timeToReact":"4.1396851","screenV":"5.98960","time":"93.05551"},{"spawnID":"213","spawnType":"Obstacle","eventType":"Collision","eventCat":"Negative","x":"-3.1296978","timeToReact":"4.1561890","screenV":"5.99295","time":"93.0720139"},{"spawnID":"214","spawnType":"Bonus","eventType":"Catch","eventCat":"Positive","x":"-2.519075","timeToReact":"4.31369","screenV":"6.52604","time":"93.41348"},{"spawnID":"205","spawnType":"Enemy","eventType":"Hurt","eventCat":"Negative","x":"-2.71920729","timeToReact":"6.7858811","screenV":"4.19301","time":"93.4985352"},{"spawnID":"205","spawnType":"Enemy","eventType":"Hurt","eventCat":"Negative","x":"-2.71920729","timeToReact":"6.7859497","screenV":"4.19296","time":"93.4986038"},{"spawnID":"215","spawnType":"Bonus","eventType":"Catch","eventCat":"Positive","x":"-1.29304445","timeToReact":"4.0752106","screenV":"6.72147","time":"93.7505646"},{"spawnID":"207","spawnType":"Obstacle","eventType":"Dodge","eventCat":"Neutral","x":"-12.024868","timeToReact":"99","screenV":"99","time":"94.0579758"},{"spawnID":"208","spawnType":"Obstacle","eventType":"Dodge","eventCat":"Neutral","x":"13.9811134","timeToReact":"99","screenV":"99","time":"94.14164"},{"spawnID":"206","spawnType":"Bonus","eventType":"Miss","eventCat":"Neutral","x":"-11.0461531","timeToReact":"99","screenV":"99","time":"94.21375"},{"spawnID":"212","spawnType":"Bonus","eventType":"Catch","eventCat":"Positive","x":"9.852316","timeToReact":"5.86010","screenV":"5.21056","time":"94.39351"},{"spawnID":"217","spawnType":"Bonus","eventType":"Catch","eventCat":"Positive","x":"11.6223688","timeToReact":"4.27393","screenV":"6.65377","time":"94.4948"},{"spawnID":"222","spawnType":"Enemy","eventType":"Hit","eventCat":"Positive","x":"0.52850914","timeToReact":"2.8890341","screenV":"5.93542","time":"94.6115341"},{"spawnID":"222","spawnType":"Enemy","eventType":"Kill","eventCat":"Positive","x":"0.52850914","timeToReact":"3.01501","screenV":"5.96705","time":"94.73751"},{"spawnID":"222","spawnType":"Enemy","eventType":"Hit","eventCat":"Positive","x":"0.52850914","timeToReact":"3.01505","screenV":"5.96697","time":"94.73755"},{"spawnID":"216","spawnType":"Enemy","eventType":"Hurt","eventCat":"Negative","x":"15.5026579","timeToReact":"5.55037","screenV":"5.12637","time":"95.59969"},{"spawnID":"216","spawnType":"Enemy","eventType":"Hurt","eventCat":"Negative","x":"15.3917923","timeToReact":"5.63756","screenV":"5.04708","time":"95.68688"},{"spawnID":"216","spawnType":"Enemy","eventType":"Hurt","eventCat":"Negative","x":"15.2365942","timeToReact":"5.70285","screenV":"4.98930","time":"95.75217"},{"spawnID":"213","spawnType":"Obstacle","eventType":"Dodge","eventCat":"Neutral","x":"-3.1296978","timeToReact":"99","screenV":"99","time":"95.76475"},{"spawnID":"216","spawnType":"Enemy","eventType":"Hurt","eventCat":"Negative","x":"15.0219164","timeToReact":"5.76775","screenV":"4.93316","time":"95.81707"},{"spawnID":"216","spawnType":"Enemy","eventType":"Hurt","eventCat":"Negative","x":"14.8278713","timeToReact":"5.81545","screenV":"4.89270","time":"95.86477"},{"spawnID":"216","spawnType":"Enemy","eventType":"Hurt","eventCat":"Negative","x":"14.5417433","timeToReact":"5.87911","screenV":"4.83972","time":"95.92843"},{"spawnID":"216","spawnType":"Enemy","eventType":"Hurt","eventCat":"Negative","x":"14.1771374","timeToReact":"5.9546854","screenV":"4.77829","time":"96.0040054"},{"spawnID":"223","spawnType":"Bonus","eventType":"Catch","eventCat":"Positive","x":"12.5654163","timeToReact":"4.1921652","screenV":"6.30606","time":"96.1385"},{"spawnID":"216","spawnType":"Enemy","eventType":"Hurt","eventCat":"Negative","x":"13.5062246","timeToReact":"6.11819","screenV":"4.65060","time":"96.16751"},{"spawnID":"216","spawnType":"Enemy","eventType":"Hurt","eventCat":"Negative","x":"12.810236","timeToReact":"6.2901347","screenV":"4.52347","time":"96.3394547"},{"spawnID":"216","spawnType":"Enemy","eventType":"Hurt","eventCat":"Negative","x":"12.3308086","timeToReact":"6.42372","screenV":"4.42940","time":"96.47304"},{"spawnID":"216","spawnType":"Enemy","eventType":"Hurt","eventCat":"Negative","x":"12.3308086","timeToReact":"6.42378","screenV":"4.42936","time":"96.4731"},{"spawnID":"216","spawnType":"Enemy","eventType":"Hurt","eventCat":"Negative","x":"12.2163763","timeToReact":"6.4501459","screenV":"4.41126","time":"96.4994659"},{"spawnID":"216","spawnType":"Enemy","eventType":"Hurt","eventCat":"Negative","x":"12.2163763","timeToReact":"6.45027","screenV":"4.41117","time":"96.49959"},{"spawnID":"216","spawnType":"Enemy","eventType":"Hurt","eventCat":"Negative","x":"11.93614","timeToReact":"6.54605","screenV":"4.34663","time":"96.59537"},{"spawnID":"216","spawnType":"Enemy","eventType":"Hurt","eventCat":"Negative","x":"11.93614","timeToReact":"6.5461542","screenV":"4.34656","time":"96.5954742"},{"spawnID":"216","spawnType":"Enemy","eventType":"Hurt","eventCat":"Negative","x":"11.7047071","timeToReact":"6.66964","screenV":"4.26608","time":"96.71896"},{"spawnID":"218","spawnType":"Obstacle","eventType":"Dodge","eventCat":"Neutral","x":"-13.8617172","timeToReact":"99","screenV":"99","time":"97.17666"},{"spawnID":"225","spawnType":"Bonus","eventType":"Catch","eventCat":"Positive","x":"11.0781622","timeToReact":"4.6765048","screenV":"6.25615","time":"97.1899948"},{"spawnID":"226","spawnType":"Bonus","eventType":"Catch","eventCat":"Positive","x":"10.8501034","timeToReact":"4.11752","screenV":"6.49474","time":"97.19008"},{"spawnID":"219","spawnType":"Bonus","eventType":"Miss","eventCat":"Neutral","x":"-9.349305","timeToReact":"99","screenV":"99","time":"98.327446"},{"spawnID":"233","spawnType":"Enemy","eventType":"Kill","eventCat":"Positive","x":"7.890254","timeToReact":"3.5904312","screenV":"4.72074","time":"98.6639557"},{"spawnID":"233","spawnType":"Enemy","eventType":"Hit","eventCat":"Positive","x":"7.890254","timeToReact":"3.5904693","screenV":"4.72069","time":"98.6639938"},{"spawnID":"221","spawnType":"Obstacle","eventType":"Dodge","eventCat":"Neutral","x":"-2.03868079","timeToReact":"99","screenV":"99","time":"98.79473"},{"spawnID":"220","spawnType":"Bonus","eventType":"Miss","eventCat":"Neutral","x":"-3.6024878","timeToReact":"99","screenV":"99","time":"98.89548"},{"spawnID":"227","spawnType":"Enemy","eventType":"Hurt","eventCat":"Negative","x":"9.876044","timeToReact":"5.6329139","screenV":"5.05125","time":"99.02891"},{"spawnID":"224","spawnType":"Obstacle","eventType":"Dodge","eventCat":"Neutral","x":"-0.804468155","timeToReact":"99","screenV":"99","time":"99.1117859"},{"spawnID":"227","spawnType":"Enemy","eventType":"Hurt","eventCat":"Negative","x":"9.5841465","timeToReact":"5.7167139","screenV":"4.97720","time":"99.11271"},{"spawnID":"227","spawnType":"Enemy","eventType":"Hurt","eventCat":"Negative","x":"9.213937","timeToReact":"5.8340139","screenV":"4.87713","time":"99.23001"},{"spawnID":"227","spawnType":"Enemy","eventType":"Hurt","eventCat":"Negative","x":"8.886415","timeToReact":"5.9017039","screenV":"4.82119","time":"99.2977"},{"spawnID":"227","spawnType":"Enemy","eventType":"Hurt","eventCat":"Negative","x":"8.45167","timeToReact":"5.9680839","screenV":"4.76757","time":"99.36408"},{"spawnID":"227","spawnType":"Enemy","eventType":"Hurt","eventCat":"Negative","x":"7.870129","timeToReact":"6.0365982","screenV":"4.71346","time":"99.4325943"},{"spawnID":"227","spawnType":"Enemy","eventType":"Hurt","eventCat":"Negative","x":"7.511979","timeToReact":"6.0691339","screenV":"4.68819","time":"99.46513"},{"spawnID":"227","spawnType":"Enemy","eventType":"Hurt","eventCat":"Negative","x":"6.7877593","timeToReact":"6.1354439","screenV":"4.63752","time":"99.53144"},{"spawnID":"227","spawnType":"Enemy","eventType":"Collision","eventCat":"Negative","x":"4.22295856","y":"-8.252764","timeToReact":"6.1707139","screenV":"4.66758","time":"99.56671"},{"spawnID":"235","spawnType":"Bonus","eventType":"Catch","eventCat":"Positive","x":"5.51525831","timeToReact":"4.22509","screenV":"6.33385","time":"99.56679"},{"spawnID":"227","spawnType":"Enemy","eventType":"Hurt","eventCat":"Negative","x":"5.026055","timeToReact":"6.3040139","screenV":"4.51351","time":"99.70001"},{"spawnID":"227","spawnType":"Enemy","eventType":"Hurt","eventCat":"Negative","x":"5.026055","timeToReact":"6.3041139","screenV":"4.51344","time":"99.70011"},{"spawnID":"227","spawnType":"Enemy","eventType":"Hurt","eventCat":"Negative","x":"4.688798","timeToReact":"6.3370590","screenV":"4.48998","time":"99.7330551"},{"spawnID":"234","spawnType":"Obstacle","eventType":"Collision","eventCat":"Negative","x":"-1.04594612","timeToReact":"4.820497","screenV":"5.95427","time":"100.003387"},{"spawnID":"236","spawnType":"Bonus","eventType":"Catch","eventCat":"Positive","x":"0.791799247","timeToReact":"4.195096","screenV":"6.33530","time":"100.100296"},{"spawnID":"229","spawnType":"Obstacle","eventType":"Dodge","eventCat":"Neutral","x":"-5.505515","timeToReact":"99","screenV":"99","time":"100.637711"},{"spawnID":"230","spawnType":"Obstacle","eventType":"Dodge","eventCat":"Neutral","x":"-6.935542","timeToReact":"99","screenV":"99","time":"100.853958"},{"spawnID":"228","spawnType":"Bonus","eventType":"Miss","eventCat":"Neutral","x":"-2.54493237","timeToReact":"99","screenV":"99","time":"101.054916"},{"spawnID":"237","spawnType":"Bonus","eventType":"Catch","eventCat":"Positive","x":"7.27154875","timeToReact":"4.8209749","screenV":"5.49144","time":"101.3114"},{"spawnID":"239","spawnType":"Obstacle","eventType":"Collision","eventCat":"Negative","x":"11.6962891","timeToReact":"4.576113","screenV":"5.97074","time":"101.422493"},{"spawnID":"241","spawnType":"Bonus","eventType":"Catch","eventCat":"Positive","x":"12.1734877","timeToReact":"4.082848","screenV":"6.74088","time":"101.725922"},{"spawnID":"231","spawnType":"Bonus","eventType":"Miss","eventCat":"Neutral","x":"-10.4303846","timeToReact":"99","screenV":"99","time":"101.775322"},{"spawnID":"234","spawnType":"Obstacle","eventType":"Dodge","eventCat":"Neutral","x":"-1.04594612","timeToReact":"99","screenV":"99","time":"101.984344"},{"spawnID":"243","spawnType":"Enemy","eventType":"Kill","eventCat":"Positive","x":"9.106432","timeToReact":"3.7503812","screenV":"4.76441","time":"102.193855"},{"spawnID":"243","spawnType":"Enemy","eventType":"Hit","eventCat":"Positive","x":"9.106432","timeToReact":"3.7504122","screenV":"4.76437","time":"102.193886"},{"spawnID":"232","spawnType":"Bonus","eventType":"Miss","eventCat":"Neutral","x":"-2.08563328","timeToReact":"99","screenV":"99","time":"102.225494"},{"spawnID":"244","spawnType":"Bonus","eventType":"Catch","eventCat":"Positive","x":"13.1211386","timeToReact":"4.493158","screenV":"6.34894","time":"103.268448"},{"spawnID":"239","spawnType":"Obstacle","eventType":"Dodge","eventCat":"Neutral","x":"11.6962891","timeToReact":"99","screenV":"99","time":"103.683914"},{"spawnID":"240","spawnType":"Bonus","eventType":"Miss","eventCat":"Neutral","x":"-3.70694923","timeToReact":"99","screenV":"99","time":"104.403786"},{"spawnID":"242","spawnType":"Bonus","eventType":"Miss","eventCat":"Neutral","x":"-12.08497","timeToReact":"99","screenV":"99","time":"105.690193"},{"spawnID":"253","spawnType":"Bonus","eventType":"Catch","eventCat":"Positive","x":"4.548185","timeToReact":"4.22184","screenV":"6.46487","time":"105.82402"},{"spawnID":"238","spawnType":"Enemy","eventType":"Miss","eventCat":"Neutral","x":"-15.4633951","y":"-24.9573669","timeToReact":"99","screenV":"99","time":"106.393"},{"spawnID":"245","spawnType":"Bonus","eventType":"Miss","eventCat":"Neutral","x":"8.022899","timeToReact":"99","screenV":"99","time":"106.796875"},{"spawnID":"247","spawnType":"Obstacle","eventType":"Dodge","eventCat":"Neutral","x":"4.533045","timeToReact":"99","screenV":"99","time":"106.894409"},{"spawnID":"249","spawnType":"Obstacle","eventType":"Dodge","eventCat":"Neutral","x":"-12.7809105","timeToReact":"99","screenV":"99","time":"107.18499"},{"spawnID":"246","spawnType":"Bonus","eventType":"Miss","eventCat":"Neutral","x":"-6.44935942","timeToReact":"99","screenV":"99","time":"107.388451"},{"spawnID":"258","spawnType":"Bonus","eventType":"Catch","eventCat":"Positive","x":"0.8731823","timeToReact":"4.279549","screenV":"6.42370","time":"107.565529"},{"spawnID":"251","spawnType":"Obstacle","eventType":"Dodge","eventCat":"Neutral","x":"-6.782484","timeToReact":"99","screenV":"99","time":"107.596779"},{"spawnID":"250","spawnType":"Bonus","eventType":"Miss","eventCat":"Neutral","x":"-9.079749","timeToReact":"99","screenV":"99","time":"107.898964"},{"spawnID":"254","spawnType":"Obstacle","eventType":"Dodge","eventCat":"Neutral","x":"8.310547","timeToReact":"99","screenV":"99","time":"108.433968"},{"spawnID":"252","spawnType":"Bonus","eventType":"Miss","eventCat":"Neutral","x":"-10.524684","timeToReact":"99","screenV":"99","time":"108.4351"},{"spawnID":"262","spawnType":"Bonus","eventType":"Catch","eventCat":"Positive","x":"11.7941942","timeToReact":"4.256271","screenV":"6.78129","time":"108.70533"},{"spawnID":"265","spawnType":"Enemy","eventType":"Kill","eventCat":"Positive","x":"8.499778","timeToReact":"3.911704","screenV":"4.72565","time":"109.055504"},{"spawnID":"265","spawnType":"Enemy","eventType":"Hit","eventCat":"Positive","x":"8.499778","timeToReact":"3.911826","screenV":"4.72550","time":"109.055626"},{"spawnID":"255","spawnType":"Enemy","eventType":"Miss","eventCat":"Neutral","x":"-8.442504","y":"-25.13636","timeToReact":"99","screenV":"99","time":"109.421394"},{"spawnID":"256","spawnType":"Bonus","eventType":"Miss","eventCat":"Neutral","x":"-10.8382378","timeToReact":"99","screenV":"99","time":"109.74427"},{"spawnID":"259","spawnType":"Enemy","eventType":"Miss","eventCat":"Neutral","x":"-6.266911","y":"-25.1522522","timeToReact":"99","screenV":"99","time":"109.7443"},{"spawnID":"267","spawnType":"Bonus","eventType":"Catch","eventCat":"Positive","x":"12.1156149","timeToReact":"4.223305","screenV":"6.36103","time":"109.826241"},{"spawnID":"270","spawnType":"Enemy","eventType":"Kill","eventCat":"Positive","x":"14.512578","timeToReact":"3.151085","screenV":"4.72891","time":"109.991325"},{"spawnID":"270","spawnType":"Enemy","eventType":"Hit","eventCat":"Positive","x":"14.512578","timeToReact":"3.151192","screenV":"4.72874","time":"109.991432"},{"spawnID":"257","spawnType":"Bonus","eventType":"Miss","eventCat":"Neutral","x":"-8.107347","timeToReact":"99","screenV":"99","time":"110.379189"},{"spawnID":"268","spawnType":"Bonus","eventType":"Catch","eventCat":"Positive","x":"4.58586","timeToReact":"4.252518","screenV":"6.22499","time":"110.411095"},{"spawnID":"261","spawnType":"Obstacle","eventType":"Dodge","eventCat":"Neutral","x":"3.38440132","timeToReact":"99","screenV":"99","time":"110.948265"},{"spawnID":"260","spawnType":"Bonus","eventType":"Miss","eventCat":"Neutral","x":"-2.46413612","timeToReact":"99","screenV":"99","time":"111.429634"},{"spawnID":"263","spawnType":"Obstacle","eventType":"Dodge","eventCat":"Neutral","x":"3.65809059","timeToReact":"99","screenV":"99","time":"111.464088"},{"spawnID":"271","spawnType":"Bonus","eventType":"Catch","eventCat":"Positive","x":"-4.93786669","timeToReact":"4.266541","screenV":"6.61890","time":"111.582985"},{"spawnID":"266","spawnType":"Obstacle","eventType":"Dodge","eventCat":"Neutral","x":"-11.6254921","timeToReact":"99","screenV":"99","time":"112.07296"},{"spawnID":"264","spawnType":"Bonus","eventType":"Miss","eventCat":"Neutral","x":"-1.47663987","timeToReact":"99","screenV":"99","time":"112.524208"},{"spawnID":"274","spawnType":"Bonus","eventType":"Catch","eventCat":"Positive","x":"2.413078","timeToReact":"4.080658","screenV":"6.34846","time":"112.524239"},{"spawnID":"273","spawnType":"Bonus","eventType":"Catch","eventCat":"Positive","x":"9.302958","timeToReact":"5.418347","screenV":"5.38826","time":"113.2963"},{"spawnID":"277","spawnType":"Bonus","eventType":"Catch","eventCat":"Positive","x":"10.0107269","timeToReact":"3.911820","screenV":"6.69985","time":"113.513161"},{"spawnID":"269","spawnType":"Bonus","eventType":"Miss","eventCat":"Neutral","x":"-10.6910095","timeToReact":"99","screenV":"99","time":"114.245338"},{"spawnID":"272","spawnType":"Obstacle","eventType":"Dodge","eventCat":"Neutral","x":"11.13158","timeToReact":"99","screenV":"99","time":"114.457558"},{"spawnID":"276","spawnType":"Bonus","eventType":"Miss","eventCat":"Neutral","x":"-11.0515051","timeToReact":"99","screenV":"99","time":"116.538628"},{"spawnID":"278","spawnType":"Obstacle","eventType":"Dodge","eventCat":"Neutral","x":"-9.98669","timeToReact":"99","screenV":"99","time":"116.570152"},{"spawnID":"275","spawnType":"Enemy","eventType":"Miss","eventCat":"Neutral","x":"11.42754","y":"-24.8813152","timeToReact":"99","screenV":"99","time":"118.122978"}]}