[{"spawnID":"1","spawnType":"Bonus","eventType":"Catch","eventCat":"Positive","x":"-1.50696421","timeToReact":"4.50678857","screenV":"6.25863","time":"6.509564"},{"spawnID":"2","spawnType":"Bonus","eventType":"Catch","eventCat":"Positive","x":"1.83688581","timeToReact":"4.47238774","screenV":"6.19695","time":"7.591397"},{"spawnID":"6","spawnType":"Bonus","eventType":"Catch","eventCat":"Positive","x":"6.019209","timeToReact":"3.89946318","screenV":"6.49449","time":"11.5230217"},{"spawnID":"3","spawnType":"Bonus","eventType":"Miss","eventCat":"Neutral","x":"-7.26120663","timeToReact":"99","screenV":"99","time":"12.0087814"},{"spawnID":"4","spawnType":"Bonus","eventType":"Miss","eventCat":"Neutral","x":"9.289194","timeToReact":"99","screenV":"99","time":"12.8915062"},{"spawnID":"7","spawnType":"Bonus","eventType":"Catch","eventCat":"Positive","x":"-0.289557338","timeToReact":"4.969307","screenV":"5.93508","time":"13.69643"},{"spawnID":"5","spawnType":"Bonus","eventType":"Miss","eventCat":"Neutral","x":"13.3822212","timeToReact":"99","screenV":"99","time":"14.0082474"},{"spawnID":"10","spawnType":"Bonus","eventType":"Catch","eventCat":"Positive","x":"3.7636342","timeToReact":"4.2147217","screenV":"6.49502","time":"16.322937"},{"spawnID":"8","spawnType":"Bonus","eventType":"Miss","eventCat":"Neutral","x":"-9.433172","timeToReact":"99","screenV":"99","time":"17.5239449"},{"spawnID":"9","spawnType":"Bonus","eventType":"Miss","eventCat":"Neutral","x":"-7.467565","timeToReact":"99","screenV":"99","time":"18.477581"},{"spawnID":"12","spawnType":"Bonus","eventType":"Catch","eventCat":"Positive","x":"-0.6286746","timeToReact":"4.1796993","screenV":"6.85440","time":"18.5117"},{"spawnID":"11","spawnType":"Bonus","eventType":"Miss","eventCat":"Neutral","x":"-11.6257763","timeToReact":"99","screenV":"99","time":"20.70752"},{"spawnID":"13","spawnType":"Bonus","eventType":"Miss","eventCat":"Neutral","x":"-12.4894629","timeToReact":"99","screenV":"99","time":"22.95625"},{"spawnID":"14","spawnType":"Bonus","eventType":"Miss","eventCat":"Neutral","x":"12.2298212","timeToReact":"99","screenV":"99","time":"24.30928"},{"spawnID":"15","spawnType":"Bonus","eventType":"Miss","eventCat":"Neutral","x":"8.123635","timeToReact":"99","screenV":"99","time":"25.3106"},{"spawnID":"16","spawnType":"Bonus","eventType":"Miss","eventCat":"Neutral","x":"7.54353","timeToReact":"99","screenV":"99","time":"26.66119"},{"spawnID":"17","spawnType":"Bonus","eventType":"Miss","eventCat":"Neutral","x":"9.857942","timeToReact":"99","screenV":"99","time":"27.3894539"},{"spawnID":"21","spawnType":"Bonus","eventType":"Catch","eventCat":"Positive","x":"-0.587734938","timeToReact":"4.1673890","screenV":"6.51354","time":"28.5901833"},{"spawnID":"18","spawnType":"Bonus","eventType":"Miss","eventCat":"Neutral","x":"-7.876482","timeToReact":"99","screenV":"99","time":"28.7226563"},{"spawnID":"19","spawnType":"Bonus","eventType":"Miss","eventCat":"Neutral","x":"6.829916","timeToReact":"99","screenV":"99","time":"29.65374"},{"spawnID":"20","spawnType":"Bonus","eventType":"Miss","eventCat":"Neutral","x":"9.99619","timeToReact":"99","screenV":"99","time":"30.8231583"},{"spawnID":"23","spawnType":"Bonus","eventType":"Catch","eventCat":"Positive","x":"0.967884541","timeToReact":"4.3002053","screenV":"6.50130","time":"30.9564667"},{"spawnID":"22","spawnType":"Bonus","eventType":"Miss","eventCat":"Neutral","x":"8.128679","timeToReact":"99","screenV":"99","time":"32.9103546"},{"spawnID":"25","spawnType":"Bonus","eventType":"Catch","eventCat":"Positive","x":"1.24208236","timeToReact":"4.1517220","screenV":"6.66550","time":"33.0559769"},{"spawnID":"24","spawnType":"Bonus","eventType":"Miss","eventCat":"Neutral","x":"-13.7938614","timeToReact":"99","screenV":"99","time":"35.4553642"},{"spawnID":"26","spawnType":"Bonus","eventType":"Catch","eventCat":"Positive","x":"-0.1705432","timeToReact":"4.0596542","screenV":"6.47625","time":"45.1889076"},{"spawnID":"27","spawnType":"Bonus","eventType":"Catch","eventCat":"Positive","x":"0.108212054","timeToReact":"4.25904","screenV":"6.56278","time":"46.52126"},{"spawnID":"29","spawnType":"Bonus","eventType":"Catch","eventCat":"Positive","x":"-1.07997191","timeToReact":"4.1100388","screenV":"6.53132","time":"48.605526"},{"spawnID":"28","spawnType":"Bonus","eventType":"Miss","eventCat":"Neutral","x":"-8.537363","timeToReact":"99","screenV":"99","time":"50.80634"},{"spawnID":"32","spawnType":"Bonus","eventType":"Catch","eventCat":"Positive","x":"-0.784415066","timeToReact":"4.1837846","screenV":"6.49488","time":"52.0532646"},{"spawnID":"30","spawnType":"Bonus","eventType":"Miss","eventCat":"Neutral","x":"11.6916418","timeToReact":"99","screenV":"99","time":"53.406147"},{"spawnID":"33","spawnType":"Bonus","eventType":"Catch","eventCat":"Positive","x":"0.759794235","timeToReact":"4.72381","screenV":"6.03740","time":"53.71832"},{"spawnID":"31","spawnType":"Bonus","eventType":"Miss","eventCat":"Neutral","x":"-6.374962","timeToReact":"99","screenV":"99","time":"54.11968"},{"spawnID":"34","spawnType":"Bonus","eventType":"Miss","eventCat":"Neutral","x":"9.969937","timeToReact":"99","screenV":"99","time":"57.5275536"},{"spawnID":"35","spawnType":"Bonus","eventType":"Miss","eventCat":"Neutral","x":"6.87426758","timeToReact":"99","screenV":"99","time":"58.689"},{"spawnID":"36","spawnType":"Bonus","eventType":"Miss","eventCat":"Neutral","x":"-6.679169","timeToReact":"99","screenV":"99","time":"59.7721672"},{"spawnID":"39","spawnType":"Bonus","eventType":"Catch","eventCat":"Positive","x":"-1.158577","timeToReact":"4.4290161","screenV":"6.34365","time":"60.1564827"},{"spawnID":"37","spawnType":"Bonus","eventType":"Miss","eventCat":"Neutral","x":"8.280211","timeToReact":"99","screenV":"99","time":"60.9926949"},{"spawnID":"38","spawnType":"Bonus","eventType":"Miss","eventCat":"Neutral","x":"-8.202545","timeToReact":"99","screenV":"99","time":"62.4090233"},{"spawnID":"43","spawnType":"Bonus","eventType":"Catch","eventCat":"Positive","x":"-0.2683068","timeToReact":"3.9961655","screenV":"6.49889","time":"64.19049"},{"spawnID":"40","spawnType":"Bonus","eventType":"Miss","eventCat":"Neutral","x":"-9.192078","timeToReact":"99","screenV":"99","time":"64.40389"},{"spawnID":"41","spawnType":"Bonus","eventType":"Miss","eventCat":"Neutral","x":"10.2868757","timeToReact":"99","screenV":"99","time":"65.4501953"},{"spawnID":"44","spawnType":"Bonus","eventType":"Catch","eventCat":"Positive","x":"-0.278465748","timeToReact":"4.48483","screenV":"6.07742","time":"65.78814"},{"spawnID":"42","spawnType":"Bonus","eventType":"Miss","eventCat":"Neutral","x":"-11.7699575","timeToReact":"99","screenV":"99","time":"66.41827"},{"spawnID":"45","spawnType":"Bonus","eventType":"Catch","eventCat":"Positive","x":"0.7719281","timeToReact":"4.65730","screenV":"6.21695","time":"67.08542"},{"spawnID":"49","spawnType":"Bonus","eventType":"Catch","eventCat":"Positive","x":"-0.9286167","timeToReact":"4.1246853","screenV":"6.48207","time":"71.0513153"},{"spawnID":"46","spawnType":"Bonus","eventType":"Miss","eventCat":"Neutral","x":"6.91084146","timeToReact":"99","screenV":"99","time":"71.0824"},{"spawnID":"47","spawnType":"Bonus","eventType":"Miss","eventCat":"Neutral","x":"5.2002","timeToReact":"99","screenV":"99","time":"72.20526"},{"spawnID":"50","spawnType":"Bonus","eventType":"Catch","eventCat":"Positive","x":"1.06353533","timeToReact":"4.15104","screenV":"6.51019","time":"72.22196"},{"spawnID":"48","spawnType":"Bonus","eventType":"Miss","eventCat":"Neutral","x":"9.379933","timeToReact":"99","screenV":"99","time":"73.34863"},{"spawnID":"51","spawnType":"Bonus","eventType":"Miss","eventCat":"Neutral","x":"-8.593488","timeToReact":"99","screenV":"99","time":"77.08817"},{"spawnID":"53","spawnType":"Bonus","eventType":"Catch","eventCat":"Positive","x":"-0.4552349","timeToReact":"4.3247257","screenV":"6.59466","time":"86.57336"},{"spawnID":"54","spawnType":"Bonus","eventType":"Catch","eventCat":"Positive","x":"0.007710911","timeToReact":"4.090186","screenV":"6.47834","time":"87.4495"},{"spawnID":"52","spawnType":"Bonus","eventType":"Miss","eventCat":"Neutral","x":"-8.029717","timeToReact":"99","screenV":"99","time":"88.62116"},{"spawnID":"55","spawnType":"Bonus","eventType":"Miss","eventCat":"Neutral","x":"-7.36030054","timeToReact":"99","screenV":"99","time":"92.01374"},{"spawnID":"56","spawnType":"Bonus","eventType":"Miss","eventCat":"Neutral","x":"-10.2467346","timeToReact":"99","screenV":"99","time":"93.11517"},{"spawnID":"57","spawnType":"Bonus","eventType":"Miss","eventCat":"Neutral","x":"-7.8402195","timeToReact":"99","screenV":"99","time":"94.06569"},{"spawnID":"58","spawnType":"Bonus","eventType":"Miss","eventCat":"Neutral","x":"9.749661","timeToReact":"99","screenV":"99","time":"95.35065"},{"spawnID":"61","spawnType":"Bonus","eventType":"Catch","eventCat":"Positive","x":"-0.75415504","timeToReact":"4.27211","screenV":"6.63476","time":"95.49621"},{"spawnID":"59","spawnType":"Bonus","eventType":"Miss","eventCat":"Neutral","x":"-6.35684729","timeToReact":"99","screenV":"99","time":"96.34851"},{"spawnID":"60","spawnType":"Bonus","eventType":"Miss","eventCat":"Neutral","x":"-6.88242","timeToReact":"99","screenV":"99","time":"97.80866"},{"spawnID":"63","spawnType":"Bonus","eventType":"Catch","eventCat":"Positive","x":"0.232040465","timeToReact":"4.40375","screenV":"6.49941","time":"97.89919"},{"spawnID":"64","spawnType":"Bonus","eventType":"Catch","eventCat":"Positive","x":"-0.463851333","timeToReact":"4.29914","screenV":"6.57888","time":"98.93406"},{"spawnID":"62","spawnType":"Bonus","eventType":"Miss","eventCat":"Neutral","x":"-9.363814","timeToReact":"99","screenV":"99","time":"99.68479"},{"spawnID":"65","spawnType":"Bonus","eventType":"Catch","eventCat":"Positive","x":"0.936927438","timeToReact":"4.2913208","screenV":"6.41713","time":"100.047966"},{"spawnID":"66","spawnType":"Bonus","eventType":"Catch","eventCat":"Positive","x":"0.12960878","timeToReact":"4.14582","screenV":"6.44967","time":"101.01226"},{"spawnID":"70","spawnType":"Bonus","eventType":"Catch","eventCat":"Positive","x":"7.440783","timeToReact":"4.166283","screenV":"6.72604","time":"105.515236"},{"spawnID":"67","spawnType":"Bonus","eventType":"Miss","eventCat":"Neutral","x":"-6.065831","timeToReact":"99","screenV":"99","time":"105.5481"},{"spawnID":"69","spawnType":"Bonus","eventType":"Catch","eventCat":"Positive","x":"11.6745729","timeToReact":"5.752090","screenV":"5.24400","time":"105.981926"},{"spawnID":"68","spawnType":"Bonus","eventType":"Miss","eventCat":"Neutral","x":"7.927245","timeToReact":"99","screenV":"99","time":"106.781288"},{"spawnID":"72","spawnType":"Bonus","eventType":"Catch","eventCat":"Positive","x":"-6.93260241","timeToReact":"4.081405","screenV":"6.69720","time":"107.681541"},{"spawnID":"73","spawnType":"Bonus","eventType":"Catch","eventCat":"Positive","x":"0.484213173","timeToReact":"4.137055","screenV":"6.50959","time":"108.848473"},{"spawnID":"71","spawnType":"Bonus","eventType":"Miss","eventCat":"Neutral","x":"13.2018566","timeToReact":"99","screenV":"99","time":"109.9419"},{"spawnID":"76","spawnType":"Bonus","eventType":"Catch","eventCat":"Positive","x":"7.97674274","timeToReact":"4.451645","screenV":"6.43835","time":"112.549141"},{"spawnID":"77","spawnType":"Bonus","eventType":"Catch","eventCat":"Positive","x":"-0.421165645","timeToReact":"3.991622","screenV":"6.84092","time":"113.213737"},{"spawnID":"74","spawnType":"Bonus","eventType":"Miss","eventCat":"Neutral","x":"13.1547594","timeToReact":"99","screenV":"99","time":"113.329155"},{"spawnID":"75","spawnType":"Bonus","eventType":"Miss","eventCat":"Neutral","x":"-6.219317","timeToReact":"99","screenV":"99","time":"114.366249"}]